{
  "title": "Botswana",
  "version": "1.1.3",
  "type": "FeatureCollection",
  "copyright": "Copyright (c) 2020 Highsoft AS, Based on data from Natural Earth",
  "copyrightShort": "Natural Earth",
  "copyrightUrl": "http://www.naturalearthdata.com",
  "crs": { "type": "name", "properties": { "name": "urn:ogc:def:crs:EPSG:32734" } },
  "hc-transform": {
    "default": {
      "crs": "+proj=utm +zone=34 +south +datum=WGS84 +units=m +no_defs",
      "scale": 0.000697517957929,
      "jsonres": 15.5,
      "jsonmarginX": -999,
      "jsonmarginY": 9851.0,
      "xoffset": 394540.458773,
      "yoffset": 8029070.36616
    }
  },
  "features": [
    {
      "type": "Feature",
      "id": "BW.6964",
      "properties": {
        "hc-group": "admin1",
        "hc-middle-x": 0.64,
        "hc-middle-y": 0.59,
        "hc-key": "bw-6964",
        "hc-a2": "LO",
        "labelrank": "4",
        "hasc": "BW.",
        "alt-name": null,
        "woe-id": "-2344749",
        "subregion": "South-East",
        "fips": "BC",
        "postal-code": null,
        "name": "Lobatse",
        "country": "Botswana",
        "type-en": "Town",
        "region": null,
        "longitude": "25.6842",
        "woe-name": null,
        "latitude": "-25.2144",
        "woe-label": null,
        "type": "Town"
      },
      "geometry": {
        "type": "Polygon",
        "coordinates": [
          [
            [5250, 971],
            [5271, 946],
            [5262, 897],
            [5218, 893],
            [5250, 971]
          ]
        ]
      }
    },
    {
      "type": "Feature",
      "id": "BW.6963",
      "properties": {
        "hc-group": "admin1",
        "hc-middle-x": 0.45,
        "hc-middle-y": 0.56,
        "hc-key": "bw-6963",
        "hc-a2": "FR",
        "labelrank": "4",
        "hasc": "BW.",
        "alt-name": null,
        "woe-id": "-2344748",
        "subregion": "North-East",
        "fips": "BC",
        "postal-code": null,
        "name": "Francistown",
        "country": "Botswana",
        "type-en": "City",
        "region": null,
        "longitude": "27.5038",
        "woe-name": null,
        "latitude": "-21.1678",
        "woe-label": null,
        "type": "City"
      },
      "geometry": {
        "type": "Polygon",
        "coordinates": [
          [
            [7512, 5663],
            [7485, 5644],
            [7386, 5659],
            [7402, 5719],
            [7494, 5774],
            [7512, 5663]
          ]
        ]
      }
    },
    {
      "type": "Feature",
      "id": "BW.6967",
      "properties": {
        "hc-group": "admin1",
        "hc-middle-x": 0.41,
        "hc-middle-y": 0.5,
        "hc-key": "bw-6967",
        "hc-a2": "SP",
        "labelrank": "4",
        "hasc": "BW.",
        "alt-name": null,
        "woe-id": "-2344741",
        "subregion": "Central",
        "fips": "BC",
        "postal-code": null,
        "name": "Selebi-Phikwe",
        "country": "Botswana",
        "type-en": "Town",
        "region": null,
        "longitude": "27.8625",
        "woe-name": null,
        "latitude": "-21.9728",
        "woe-label": null,
        "type": "Town"
      },
      "geometry": {
        "type": "Polygon",
        "coordinates": [
          [
            [7838, 4731],
            [7755, 4691],
            [7754, 4729],
            [7821, 4780],
            [7838, 4731]
          ]
        ]
      }
    },
    {
      "type": "Feature",
      "id": "BW.6966",
      "properties": {
        "hc-group": "admin1",
        "hc-middle-x": 0.52,
        "hc-middle-y": 0.36,
        "hc-key": "bw-6966",
        "hc-a2": "SO",
        "labelrank": "4",
        "hasc": "BW.",
        "alt-name": null,
        "woe-id": "-2344741",
        "subregion": "Central",
        "fips": "BC",
        "postal-code": null,
        "name": "Sowa",
        "country": "Botswana",
        "type-en": "Township",
        "region": null,
        "longitude": "26.1919",
        "woe-name": null,
        "latitude": "-20.5752",
        "woe-label": null,
        "type": "Township"
      },
      "geometry": {
        "type": "Polygon",
        "coordinates": [
          [
            [5944, 6505],
            [6070, 6485],
            [6065, 6438],
            [5917, 6480],
            [5944, 6505]
          ]
        ]
      }
    },
    {
      "type": "Feature",
      "id": "BW.KG",
      "properties": {
        "hc-group": "admin1",
        "hc-middle-x": 0.44,
        "hc-middle-y": 0.44,
        "hc-key": "bw-kg",
        "hc-a2": "KG",
        "labelrank": "4",
        "hasc": "BW.KG",
        "alt-name": null,
        "woe-id": "2344744",
        "subregion": "Kgalagadi",
        "fips": "BC04",
        "postal-code": "KG",
        "name": "Kgalagadi",
        "country": "Botswana",
        "type-en": "District",
        "region": null,
        "longitude": "22.2402",
        "woe-name": "Kgalagadi",
        "latitude": "-24.8361",
        "woe-label": "Kgalagadi, BW, Botswana",
        "type": "District"
      },
      "geometry": {
        "type": "Polygon",
        "coordinates": [
          [
            [3938, 309],
            [3891, 328],
            [3817, 310],
            [3718, 356],
            [3645, 447],
            [3541, 477],
            [3404, 446],
            [3373, 491],
            [3316, 478],
            [3232, 552],
            [3123, 673],
            [3062, 693],
            [2819, 904],
            [2717, 897],
            [2608, 930],
            [2502, 912],
            [2396, 859],
            [2326, 878],
            [2230, 784],
            [2146, 677],
            [2110, 565],
            [2099, 430],
            [2035, 350],
            [2054, 264],
            [1992, 188],
            [2002, 76],
            [1939, 33],
            [1942, -4],
            [1849, -117],
            [1810, -189],
            [1684, -210],
            [1590, -318],
            [1498, -346],
            [1432, -421],
            [1376, -558],
            [1280, -675],
            [1148, -729],
            [981, -745],
            [972, -875],
            [879, -957],
            [677, -945],
            [550, -918],
            [273, -967],
            [131, -935],
            [42, -889],
            [-18, -897],
            [-191, -999],
            [-247, -910],
            [-280, -753],
            [-256, -672],
            [-284, -587],
            [-266, -443],
            [-219, -400],
            [-125, -262],
            [-30, -88],
            [-71, -16],
            [-82, 196],
            [-143, 310],
            [-177, 410],
            [-216, 433],
            [-246, 532],
            [-216, 558],
            [-273, 633],
            [-281, 750],
            [-357, 808],
            [-383, 915],
            [-423, 989],
            [-475, 1026],
            [-464, 1064],
            [-552, 1225],
            [-693, 1341],
            [-821, 1398],
            [-919, 1484],
            [-972, 1559],
            [-987, 3287],
            [-965, 3287],
            [2416, 3272],
            [2398, 3169],
            [2305, 3137],
            [2300, 2977],
            [2384, 2963],
            [2402, 2875],
            [2399, 2448],
            [2380, 1461],
            [2419, 1428],
            [3467, 1414],
            [3518, 1393],
            [3641, 1259],
            [3670, 1193],
            [3674, 623],
            [3831, 445],
            [3926, 411],
            [3938, 309]
          ]
        ]
      }
    },
    {
      "type": "Feature",
      "id": "BW.SE",
      "properties": {
        "hc-group": "admin1",
        "hc-middle-x": 0.45,
        "hc-middle-y": 0.46,
        "hc-key": "bw-se",
        "hc-a2": "SE",
        "labelrank": "4",
        "hasc": "BW.SE",
        "alt-name": "Borwa-Botlhaba",
        "woe-id": "2344749",
        "subregion": "South-East",
        "fips": "BC09",
        "postal-code": "SE",
        "name": "South-East",
        "country": "Botswana",
        "type-en": "District",
        "region": null,
        "longitude": "25.7446",
        "woe-name": "South-East",
        "latitude": "-24.9869",
        "woe-label": "South-East, BW, Botswana",
        "type": "District"
      },
      "geometry": {
        "type": "Polygon",
        "coordinates": [
          [
            [5798, 1566],
            [5629, 1520],
            [5575, 1487],
            [5467, 1473],
            [5471, 1307],
            [5420, 1153],
            [5255, 806],
            [5202, 623],
            [5089, 674],
            [5084, 701],
            [5224, 1133],
            [5228, 1165],
            [5162, 1180],
            [5206, 1331],
            [5245, 1370],
            [5268, 1455],
            [5436, 1625],
            [5457, 1521],
            [5567, 1519],
            [5657, 1694],
            [5741, 1631],
            [5798, 1566]
          ],
          [
            [5250, 971],
            [5218, 893],
            [5262, 897],
            [5271, 946],
            [5250, 971]
          ]
        ]
      }
    },
    {
      "type": "Feature",
      "id": "BW.NE",
      "properties": {
        "hc-group": "admin1",
        "hc-middle-x": 0.33,
        "hc-middle-y": 0.33,
        "hc-key": "bw-ne",
        "hc-a2": "NE",
        "labelrank": "4",
        "hasc": "BW.NE",
        "alt-name": null,
        "woe-id": "2344748",
        "subregion": "North-East",
        "fips": "BC08",
        "postal-code": "NE",
        "name": "North-East",
        "country": "Botswana",
        "type-en": "District",
        "region": null,
        "longitude": "27.4487",
        "woe-name": "North-East",
        "latitude": "-20.9374",
        "woe-label": "North-East, BW, Botswana",
        "type": "District"
      },
      "geometry": {
        "type": "Polygon",
        "coordinates": [
          [
            [7219, 6521],
            [7302, 6545],
            [7520, 6525],
            [7585, 6534],
            [7705, 6486],
            [7707, 6417],
            [7681, 6332],
            [7705, 6236],
            [7684, 6091],
            [7662, 6057],
            [7649, 5788],
            [7702, 5714],
            [7778, 5653],
            [7885, 5496],
            [7944, 5343],
            [7928, 5309],
            [7981, 5217],
            [7897, 5228],
            [7835, 5265],
            [7683, 5263],
            [7589, 5293],
            [7509, 5296],
            [7423, 5342],
            [7334, 5491],
            [7314, 5602],
            [7236, 5836],
            [7154, 5984],
            [7146, 6188],
            [7219, 6441],
            [7219, 6521]
          ],
          [
            [7512, 5663],
            [7494, 5774],
            [7402, 5719],
            [7386, 5659],
            [7485, 5644],
            [7512, 5663]
          ]
        ]
      }
    },
    {
      "type": "Feature",
      "id": "BW.6962",
      "properties": {
        "hc-group": "admin1",
        "hc-middle-x": 0.22,
        "hc-middle-y": 0.91,
        "hc-key": "bw-6962",
        "hc-a2": "GA",
        "labelrank": "4",
        "hasc": "BW.",
        "alt-name": null,
        "woe-id": "-2344749",
        "subregion": "South-East",
        "fips": "BC",
        "postal-code": null,
        "name": "Gaborone",
        "country": "Botswana",
        "type-en": "City",
        "region": null,
        "longitude": "25.9171",
        "woe-name": null,
        "latitude": "-24.6239",
        "woe-label": null,
        "type": "City"
      },
      "geometry": {
        "type": "Polygon",
        "coordinates": [
          [
            [5657, 1694],
            [5567, 1519],
            [5457, 1521],
            [5436, 1625],
            [5569, 1759],
            [5657, 1694]
          ]
        ]
      }
    },
    {
      "type": "Feature",
      "id": "BW.GH",
      "properties": {
        "hc-group": "admin1",
        "hc-middle-x": 0.44,
        "hc-middle-y": 0.49,
        "hc-key": "bw-gh",
        "hc-a2": "GH",
        "labelrank": "6",
        "hasc": "BW.GH",
        "alt-name": "Ghantsi",
        "woe-id": "2344743",
        "subregion": "Ghanzi",
        "fips": "BC03",
        "postal-code": "GH",
        "name": "Ghanzi",
        "country": "Botswana",
        "type-en": "District",
        "region": null,
        "longitude": "22.7086",
        "woe-name": "Ghanzi",
        "latitude": "-22.1555",
        "woe-label": "Ghanzi, BW, Botswana",
        "type": "District"
      },
      "geometry": {
        "type": "Polygon",
        "coordinates": [
          [
            [2416, 3272],
            [-965, 3287],
            [-987, 3287],
            [-999, 4853],
            [110, 4856],
            [124, 4900],
            [120, 6054],
            [141, 6054],
            [3380, 6025],
            [5065, 3644],
            [4833, 3210],
            [2416, 3272]
          ]
        ]
      }
    },
    {
      "type": "Feature",
      "id": "BW.NW",
      "properties": {
        "hc-group": "admin1",
        "hc-middle-x": 0.34,
        "hc-middle-y": 0.53,
        "hc-key": "bw-nw",
        "hc-a2": "NW",
        "labelrank": "4",
        "hasc": "BW.NW",
        "alt-name": "North West|Bokone-Bophirima",
        "woe-id": "55949048",
        "subregion": "North-West",
        "fips": "BC08",
        "postal-code": "NW",
        "name": "North-West",
        "country": "Botswana",
        "type-en": "District",
        "region": null,
        "longitude": "23.4709",
        "woe-name": "North-West",
        "latitude": "-19.6141",
        "woe-label": "North-West, BW, Botswana",
        "type": "District"
      },
      "geometry": {
        "type": "Polygon",
        "coordinates": [
          [
            [3380, 6025],
            [141, 6054],
            [120, 6054],
            [113, 8445],
            [113, 9261],
            [685, 9284],
            [2409, 9607],
            [2723, 9630],
            [2787, 9615],
            [2841, 9483],
            [2959, 9354],
            [3001, 9339],
            [3067, 9205],
            [3051, 9180],
            [3101, 9050],
            [3243, 9118],
            [3352, 9233],
            [3472, 9334],
            [3476, 9376],
            [3539, 9395],
            [3639, 9471],
            [3729, 9510],
            [3785, 9576],
            [3849, 9599],
            [3915, 9578],
            [3996, 9667],
            [4060, 9659],
            [4154, 9533],
            [4237, 9550],
            [4410, 9725],
            [4521, 9790],
            [4648, 9822],
            [4674, 9848],
            [4735, 9802],
            [4866, 9814],
            [4905, 9851],
            [5026, 9834],
            [4977, 9732],
            [4984, 9669],
            [5060, 9503],
            [5163, 9417],
            [5256, 9217],
            [5294, 9101],
            [5421, 8976],
            [5473, 8896],
            [5577, 8817],
            [5593, 8686],
            [5632, 8595],
            [5771, 8462],
            [5800, 8365],
            [4685, 8395],
            [4659, 7202],
            [4850, 7111],
            [4858, 7091],
            [4842, 6812],
            [4822, 6782],
            [4097, 6739],
            [3981, 6729],
            [3847, 6862],
            [3817, 6924],
            [3766, 6925],
            [3709, 6978],
            [3560, 6922],
            [3524, 6861],
            [3392, 6843],
            [3380, 6025]
          ]
        ]
      }
    },
    {
      "type": "Feature",
      "id": "BW.CE",
      "properties": {
        "hc-group": "admin1",
        "hc-middle-x": 0.44,
        "hc-middle-y": 0.55,
        "hc-key": "bw-ce",
        "hc-a2": "CE",
        "labelrank": "4",
        "hasc": "BW.CE",
        "alt-name": "Centre|Ngwato|Serowe-Palapye",
        "woe-id": "2344741",
        "subregion": "Central",
        "fips": "BC01",
        "postal-code": "CE",
        "name": "Central",
        "country": "Botswana",
        "type-en": "District",
        "region": null,
        "longitude": "26.6144",
        "woe-name": "Central",
        "latitude": "-21.8775",
        "woe-label": "Central, BW, Botswana",
        "type": "District"
      },
      "geometry": {
        "type": "Polygon",
        "coordinates": [
          [
            [5065, 3644],
            [3380, 6025],
            [3392, 6843],
            [3524, 6861],
            [3560, 6922],
            [3709, 6978],
            [3766, 6925],
            [3817, 6924],
            [3847, 6862],
            [3981, 6729],
            [4097, 6739],
            [4822, 6782],
            [4842, 6812],
            [4858, 7091],
            [4850, 7111],
            [4659, 7202],
            [4685, 8395],
            [5800, 8365],
            [5771, 8272],
            [5783, 8220],
            [5867, 8072],
            [5967, 7760],
            [6038, 7687],
            [6150, 7669],
            [6194, 7618],
            [6169, 7573],
            [6251, 7537],
            [6302, 7467],
            [6388, 7437],
            [6452, 7385],
            [6483, 7318],
            [6571, 7281],
            [6634, 7216],
            [6725, 7200],
            [6851, 7130],
            [6966, 7115],
            [7058, 7036],
            [7141, 7022],
            [7176, 6987],
            [7228, 6836],
            [7243, 6694],
            [7219, 6521],
            [7219, 6441],
            [7146, 6188],
            [7154, 5984],
            [7236, 5836],
            [7314, 5602],
            [7334, 5491],
            [7423, 5342],
            [7509, 5296],
            [7589, 5293],
            [7683, 5263],
            [7835, 5265],
            [7897, 5228],
            [7981, 5217],
            [8027, 5184],
            [8176, 5156],
            [8310, 5148],
            [8509, 5062],
            [8611, 5085],
            [8695, 5063],
            [8949, 4923],
            [9146, 4863],
            [9166, 4825],
            [9117, 4744],
            [9115, 4642],
            [9166, 4556],
            [9248, 4523],
            [9354, 4520],
            [9389, 4455],
            [9471, 4376],
            [9328, 4389],
            [9266, 4354],
            [9130, 4354],
            [9026, 4251],
            [9030, 4166],
            [8963, 4081],
            [8889, 4089],
            [8853, 4039],
            [8756, 4019],
            [8633, 3966],
            [8518, 3945],
            [8449, 3967],
            [8313, 3956],
            [8210, 3875],
            [8148, 3859],
            [8106, 3756],
            [8037, 3689],
            [7973, 3668],
            [7939, 3561],
            [7843, 3521],
            [7849, 3442],
            [7790, 3384],
            [7652, 3336],
            [7667, 3288],
            [7624, 3222],
            [7564, 3257],
            [7505, 3219],
            [7462, 3234],
            [7389, 3064],
            [7234, 3037],
            [7177, 2999],
            [7166, 3037],
            [7083, 2954],
            [6997, 2923],
            [6999, 2886],
            [6913, 2887],
            [6850, 2786],
            [6842, 2732],
            [6770, 2748],
            [6721, 2628],
            [6651, 2579],
            [6637, 2605],
            [6577, 2506],
            [6535, 2502],
            [6438, 2398],
            [5685, 2885],
            [5543, 3102],
            [5495, 3153],
            [5376, 3203],
            [5065, 3644]
          ],
          [
            [7838, 4731],
            [7821, 4780],
            [7754, 4729],
            [7755, 4691],
            [7838, 4731]
          ],
          [
            [5944, 6505],
            [5917, 6480],
            [6065, 6438],
            [6070, 6485],
            [5944, 6505]
          ]
        ]
      }
    },
    {
      "type": "Feature",
      "id": "BW.KL",
      "properties": {
        "hc-group": "admin1",
        "hc-middle-x": 0.45,
        "hc-middle-y": 0.56,
        "hc-key": "bw-kl",
        "hc-a2": "KL",
        "labelrank": "4",
        "hasc": "BW.KL",
        "alt-name": null,
        "woe-id": "2344745",
        "subregion": "Kgatleng",
        "fips": "BC05",
        "postal-code": "KL",
        "name": "Kgatleng",
        "country": "Botswana",
        "type-en": "District",
        "region": null,
        "longitude": "26.4263",
        "woe-name": "Kgatleng",
        "latitude": "-24.2001",
        "woe-label": "Kgatleng, BW, Botswana",
        "type": "District"
      },
      "geometry": {
        "type": "Polygon",
        "coordinates": [
          [
            [5685, 2885],
            [6438, 2398],
            [6535, 2502],
            [6577, 2506],
            [6637, 2605],
            [6651, 2579],
            [6721, 2628],
            [6599, 2189],
            [6569, 2031],
            [6515, 1984],
            [6416, 1956],
            [6312, 1860],
            [6208, 1793],
            [6135, 1660],
            [6060, 1589],
            [5975, 1605],
            [5798, 1566],
            [5741, 1631],
            [5657, 1694],
            [5569, 1759],
            [5508, 1795],
            [5501, 1853],
            [5549, 1981],
            [5589, 2156],
            [5685, 2885]
          ]
        ]
      }
    },
    {
      "type": "Feature",
      "id": "BW.KW",
      "properties": {
        "hc-group": "admin1",
        "hc-middle-x": 0.53,
        "hc-middle-y": 0.49,
        "hc-key": "bw-kw",
        "hc-a2": "KW",
        "labelrank": "4",
        "hasc": "BW.KW",
        "alt-name": null,
        "woe-id": "2344746",
        "subregion": "Kweneng",
        "fips": "BC06",
        "postal-code": "KW",
        "name": "Kweneng",
        "country": "Botswana",
        "type-en": "District",
        "region": null,
        "longitude": "24.4879",
        "woe-name": "Kweneng",
        "latitude": "-23.8665",
        "woe-label": "Kweneng, BW, Botswana",
        "type": "District"
      },
      "geometry": {
        "type": "Polygon",
        "coordinates": [
          [
            [5685, 2885],
            [5589, 2156],
            [5549, 1981],
            [5501, 1853],
            [5508, 1795],
            [5569, 1759],
            [5436, 1625],
            [5268, 1455],
            [5156, 1467],
            [5029, 1543],
            [4320, 1793],
            [4131, 1859],
            [2399, 2448],
            [2402, 2875],
            [2384, 2963],
            [2300, 2977],
            [2305, 3137],
            [2398, 3169],
            [2416, 3272],
            [4833, 3210],
            [5065, 3644],
            [5376, 3203],
            [5495, 3153],
            [5543, 3102],
            [5685, 2885]
          ]
        ]
      }
    },
    {
      "type": "Feature",
      "id": "BW.6965",
      "properties": {
        "hc-group": "admin1",
        "hc-middle-x": 0.52,
        "hc-middle-y": 0.51,
        "hc-key": "bw-6965",
        "hc-a2": "JW",
        "labelrank": "4",
        "hasc": "BW.",
        "alt-name": null,
        "woe-id": "-2344750",
        "subregion": "Southern",
        "fips": "BC",
        "postal-code": null,
        "name": "Jwaneng",
        "country": "Botswana",
        "type-en": "Town",
        "region": null,
        "longitude": "24.7253",
        "woe-name": null,
        "latitude": "-24.5774",
        "woe-label": null,
        "type": "Town"
      },
      "geometry": {
        "type": "Polygon",
        "coordinates": [
          [
            [4131, 1859],
            [4320, 1793],
            [4323, 1625],
            [4122, 1620],
            [4131, 1859]
          ]
        ]
      }
    },
    {
      "type": "Feature",
      "id": "BW.SO",
      "properties": {
        "hc-group": "admin1",
        "hc-middle-x": 0.69,
        "hc-middle-y": 0.62,
        "hc-key": "bw-so",
        "hc-a2": "SO",
        "labelrank": "4",
        "hasc": "BW.SO",
        "alt-name": "Borwa|Ngwakets|Ngwaketse",
        "woe-id": "2344750",
        "subregion": "Southern",
        "fips": "BC10",
        "postal-code": "SO",
        "name": "Southern",
        "country": "Botswana",
        "type-en": "District",
        "region": null,
        "longitude": "24.3683",
        "woe-name": "Southern",
        "latitude": "-25.0004",
        "woe-label": "Southern, BW, Botswana",
        "type": "District"
      },
      "geometry": {
        "type": "Polygon",
        "coordinates": [
          [
            [2399, 2448],
            [4131, 1859],
            [4122, 1620],
            [4323, 1625],
            [4320, 1793],
            [5029, 1543],
            [5156, 1467],
            [5268, 1455],
            [5245, 1370],
            [5206, 1331],
            [5162, 1180],
            [5228, 1165],
            [5224, 1133],
            [5084, 701],
            [5089, 674],
            [5202, 623],
            [5124, 438],
            [4980, 333],
            [4901, 297],
            [4673, 281],
            [4537, 316],
            [4445, 288],
            [4379, 241],
            [4259, 214],
            [4114, 225],
            [3938, 309],
            [3926, 411],
            [3831, 445],
            [3674, 623],
            [3670, 1193],
            [3641, 1259],
            [3518, 1393],
            [3467, 1414],
            [2419, 1428],
            [2380, 1461],
            [2399, 2448]
          ]
        ]
      }
    }
  ]
}
