{
  "title": "Hungary",
  "version": "1.1.3",
  "type": "FeatureCollection",
  "copyright": "Copyright (c) 2020 Highsoft AS, Based on data from Natural Earth",
  "copyrightShort": "Natural Earth",
  "copyrightUrl": "http://www.naturalearthdata.com",
  "crs": { "type": "name", "properties": { "name": "urn:ogc:def:crs:EPSG:32634" } },
  "hc-transform": {
    "default": {
      "crs": "+proj=utm +zone=34 +datum=WGS84 +units=m +no_defs",
      "scale": 0.00136158891591,
      "jsonres": 15.5,
      "jsonmarginX": -999,
      "jsonmarginY": 9851.0,
      "xoffset": 126096.872432,
      "yoffset": 5379573.64137
    }
  },
  "features": [
    {
      "type": "Feature",
      "id": "HU.NO",
      "properties": {
        "hc-group": "admin1",
        "hc-middle-x": 0.5,
        "hc-middle-y": 0.48,
        "hc-key": "hu-no",
        "hc-a2": "NO",
        "labelrank": "7",
        "hasc": "HU.NO",
        "alt-name": null,
        "woe-id": "12577922",
        "subregion": "Nógrád",
        "fips": "HU14",
        "postal-code": "NO",
        "name": "Nógrád",
        "country": "Hungary",
        "type-en": "County",
        "region": "Northern Hungary",
        "longitude": "19.5146",
        "woe-name": "Nógrád",
        "latitude": "47.9662",
        "woe-label": "Nógrád, HU, Hungary",
        "type": "Megye"
      },
      "geometry": {
        "type": "Polygon",
        "coordinates": [
          [
            [5172, 8819],
            [5210, 8832],
            [5282, 8898],
            [5383, 8941],
            [5399, 8919],
            [5473, 8855],
            [5364, 8773],
            [5297, 8747],
            [5352, 8630],
            [5362, 8552],
            [5314, 8547],
            [5276, 8513],
            [5248, 8401],
            [5163, 8332],
            [5115, 8354],
            [5075, 8277],
            [5035, 8249],
            [4985, 8279],
            [4940, 8248],
            [4858, 8113],
            [4798, 8094],
            [4646, 7920],
            [4548, 7903],
            [4452, 7850],
            [4440, 8005],
            [4390, 8124],
            [4329, 8154],
            [3994, 8225],
            [3866, 8225],
            [3674, 8369],
            [3639, 8453],
            [3695, 8501],
            [3693, 8610],
            [3642, 8687],
            [3742, 8712],
            [3808, 8707],
            [3903, 8718],
            [4097, 8690],
            [4210, 8751],
            [4422, 8742],
            [4507, 8800],
            [4544, 8983],
            [4589, 9032],
            [4734, 9067],
            [4766, 9062],
            [4833, 8995],
            [4942, 9001],
            [4969, 8967],
            [4956, 8904],
            [4903, 8840],
            [4864, 8650],
            [4987, 8625],
            [5032, 8701],
            [5108, 8753],
            [5172, 8819]
          ]
        ]
      }
    },
    {
      "type": "Feature",
      "id": "HU.BZ",
      "properties": {
        "hc-group": "admin1",
        "hc-middle-x": 0.52,
        "hc-middle-y": 0.35,
        "hc-key": "hu-bz",
        "hc-a2": "BZ",
        "labelrank": "7",
        "hasc": "HU.BZ",
        "alt-name": null,
        "woe-id": "12577914",
        "subregion": "Borsod-Abaúj-Zemplén",
        "fips": "HU04",
        "postal-code": "BZ",
        "name": "Borsod-Abaúj-Zemplén",
        "country": "Hungary",
        "type-en": "County",
        "region": "Northern Hungary",
        "longitude": "21.0983",
        "woe-name": "Borsod-Abaúj-Zemplén",
        "latitude": "48.2104",
        "woe-label": "Borsod-Abaúj-Zemplén, HU, Hungary",
        "type": "Megye"
      },
      "geometry": {
        "type": "Polygon",
        "coordinates": [
          [
            [5473, 8855],
            [5399, 8919],
            [5383, 8941],
            [5476, 8989],
            [5536, 9102],
            [5593, 9095],
            [5685, 9157],
            [5752, 9113],
            [5834, 9177],
            [5907, 9304],
            [5969, 9490],
            [6011, 9557],
            [6084, 9641],
            [6084, 9752],
            [6129, 9770],
            [6226, 9776],
            [6556, 9851],
            [6605, 9839],
            [6651, 9796],
            [6723, 9785],
            [6808, 9733],
            [6902, 9731],
            [6992, 9703],
            [7063, 9663],
            [7183, 9721],
            [7235, 9733],
            [7300, 9697],
            [7363, 9783],
            [7393, 9801],
            [7473, 9808],
            [7553, 9834],
            [7657, 9785],
            [7706, 9692],
            [7815, 9676],
            [7850, 9552],
            [7951, 9394],
            [8030, 9321],
            [8127, 9309],
            [8207, 9351],
            [8275, 9362],
            [8345, 9399],
            [8483, 9417],
            [8606, 9418],
            [8662, 9478],
            [8701, 9473],
            [8669, 9436],
            [8581, 9258],
            [8538, 9231],
            [8465, 9237],
            [8370, 9106],
            [8317, 9075],
            [8218, 9068],
            [8138, 8996],
            [8094, 8989],
            [7975, 8913],
            [7915, 8913],
            [7853, 8942],
            [7639, 8933],
            [7593, 8888],
            [7562, 8781],
            [7588, 8710],
            [7572, 8636],
            [7532, 8596],
            [7479, 8580],
            [7339, 8578],
            [7290, 8628],
            [7242, 8584],
            [7177, 8578],
            [7109, 8532],
            [7081, 8485],
            [7071, 8423],
            [7060, 8371],
            [6981, 8259],
            [6984, 8175],
            [6970, 8120],
            [6937, 8085],
            [6946, 7999],
            [6859, 7983],
            [6801, 7856],
            [6721, 7775],
            [6606, 7764],
            [6562, 7760],
            [6534, 7748],
            [6446, 7780],
            [6273, 7816],
            [6240, 7871],
            [6220, 7944],
            [6147, 8030],
            [6047, 8210],
            [6022, 8239],
            [6048, 8282],
            [6042, 8328],
            [5992, 8398],
            [5982, 8447],
            [6072, 8553],
            [6093, 8647],
            [6152, 8685],
            [6231, 8702],
            [6327, 8707],
            [6378, 8636],
            [6545, 8523],
            [6688, 8552],
            [6740, 8611],
            [6732, 8665],
            [6696, 8730],
            [6697, 8801],
            [6665, 8890],
            [6621, 8955],
            [6562, 8991],
            [6506, 8991],
            [6439, 9039],
            [6275, 8916],
            [6199, 8851],
            [6116, 8845],
            [6064, 8784],
            [5979, 8874],
            [5878, 8743],
            [5825, 8782],
            [5768, 8779],
            [5723, 8739],
            [5668, 8740],
            [5622, 8795],
            [5574, 8800],
            [5508, 8870],
            [5473, 8855]
          ]
        ]
      }
    },
    {
      "type": "Feature",
      "id": "HU.HE",
      "properties": {
        "hc-group": "admin1",
        "hc-middle-x": 0.6,
        "hc-middle-y": 0.55,
        "hc-key": "hu-he",
        "hc-a2": "HE",
        "labelrank": "7",
        "hasc": "HU.HE",
        "alt-name": null,
        "woe-id": "12577920",
        "subregion": "Heves",
        "fips": "HU11",
        "postal-code": "HE",
        "name": "Heves",
        "country": "Hungary",
        "type-en": "County",
        "region": "Northern Hungary",
        "longitude": "20.1774",
        "woe-name": "Heves",
        "latitude": "47.8614",
        "woe-label": "Heves, HU, Hungary",
        "type": "Megye"
      },
      "geometry": {
        "type": "Polygon",
        "coordinates": [
          [
            [6093, 8647],
            [6072, 8553],
            [5982, 8447],
            [5939, 8500],
            [5925, 8611],
            [5850, 8627],
            [5825, 8545],
            [5785, 8524],
            [5813, 8360],
            [5792, 8264],
            [5791, 8167],
            [5826, 8078],
            [5896, 8077],
            [5931, 8122],
            [5932, 8188],
            [5967, 8225],
            [6022, 8239],
            [6047, 8210],
            [6147, 8030],
            [6220, 7944],
            [6240, 7871],
            [6273, 7816],
            [6446, 7780],
            [6534, 7748],
            [6496, 7678],
            [6432, 7644],
            [6441, 7616],
            [6409, 7582],
            [6399, 7526],
            [6117, 7338],
            [6094, 7270],
            [6014, 7231],
            [5971, 7183],
            [5896, 7182],
            [5805, 7243],
            [5760, 7321],
            [5771, 7373],
            [5745, 7447],
            [5684, 7480],
            [5617, 7600],
            [5466, 7560],
            [5505, 7509],
            [5427, 7488],
            [5343, 7547],
            [5318, 7637],
            [5307, 7732],
            [5245, 7753],
            [5169, 7730],
            [5133, 7741],
            [5017, 7598],
            [4962, 7631],
            [4876, 7624],
            [4790, 7586],
            [4766, 7655],
            [4694, 7763],
            [4678, 7807],
            [4708, 7868],
            [4646, 7920],
            [4798, 8094],
            [4858, 8113],
            [4940, 8248],
            [4985, 8279],
            [5035, 8249],
            [5075, 8277],
            [5115, 8354],
            [5163, 8332],
            [5248, 8401],
            [5276, 8513],
            [5314, 8547],
            [5362, 8552],
            [5352, 8630],
            [5297, 8747],
            [5364, 8773],
            [5473, 8855],
            [5508, 8870],
            [5574, 8800],
            [5622, 8795],
            [5668, 8740],
            [5723, 8739],
            [5768, 8779],
            [5825, 8782],
            [5878, 8743],
            [5979, 8874],
            [6064, 8784],
            [6091, 8756],
            [6093, 8647]
          ]
        ]
      }
    },
    {
      "type": "Feature",
      "id": "HU.JN",
      "properties": {
        "hc-group": "admin1",
        "hc-middle-x": 0.69,
        "hc-middle-y": 0.43,
        "hc-key": "hu-jn",
        "hc-a2": "JN",
        "labelrank": "7",
        "hasc": "HU.JN",
        "alt-name": null,
        "woe-id": "12577926",
        "subregion": "Jász-Nagykun-Szolnok",
        "fips": "HU20",
        "postal-code": "JN",
        "name": "Jász-Nagykun-Szolnok",
        "country": "Hungary",
        "type-en": "County",
        "region": "Northern Great Plain",
        "longitude": "20.5204",
        "woe-name": "Jász-Nagykun-Szolnok",
        "latitude": "47.2052",
        "woe-label": "Jász-Nagykun-Szolnok, HU, Hungary",
        "type": "Megye"
      },
      "geometry": {
        "type": "Polygon",
        "coordinates": [
          [
            [6534, 7748],
            [6562, 7760],
            [6606, 7764],
            [6642, 7645],
            [6704, 7582],
            [6806, 7551],
            [6855, 7505],
            [6876, 7410],
            [6895, 7212],
            [6922, 7101],
            [6937, 6990],
            [6929, 6841],
            [6883, 6724],
            [6852, 6708],
            [6799, 6620],
            [6760, 6605],
            [6730, 6545],
            [6670, 6493],
            [6606, 6491],
            [6466, 6323],
            [6473, 6278],
            [6412, 6205],
            [6436, 6062],
            [6419, 5992],
            [6306, 5942],
            [6261, 5987],
            [6224, 5955],
            [6177, 5968],
            [6131, 5904],
            [6020, 5913],
            [5957, 5858],
            [5939, 5790],
            [5963, 5712],
            [5853, 5663],
            [5800, 5622],
            [5741, 5639],
            [5684, 5694],
            [5498, 5634],
            [5380, 5712],
            [5307, 5719],
            [5279, 5770],
            [5328, 5886],
            [5432, 5903],
            [5456, 5946],
            [5424, 6005],
            [5504, 5972],
            [5533, 6030],
            [5466, 6051],
            [5466, 6088],
            [5522, 6129],
            [5612, 6195],
            [5511, 6235],
            [5423, 6315],
            [5373, 6422],
            [5382, 6536],
            [5475, 6516],
            [5554, 6455],
            [5644, 6407],
            [5725, 6418],
            [5774, 6454],
            [5779, 6531],
            [5723, 6555],
            [5691, 6623],
            [5753, 6689],
            [5713, 6769],
            [5604, 6859],
            [5509, 6979],
            [5394, 6849],
            [5331, 6764],
            [5303, 6808],
            [5308, 6919],
            [5295, 6952],
            [4918, 7340],
            [4911, 7422],
            [4851, 7417],
            [4801, 7451],
            [4772, 7517],
            [4790, 7586],
            [4876, 7624],
            [4962, 7631],
            [5017, 7598],
            [5133, 7741],
            [5169, 7730],
            [5245, 7753],
            [5307, 7732],
            [5318, 7637],
            [5343, 7547],
            [5427, 7488],
            [5505, 7509],
            [5466, 7560],
            [5617, 7600],
            [5684, 7480],
            [5745, 7447],
            [5771, 7373],
            [5760, 7321],
            [5805, 7243],
            [5896, 7182],
            [5971, 7183],
            [6014, 7231],
            [6094, 7270],
            [6117, 7338],
            [6399, 7526],
            [6409, 7582],
            [6441, 7616],
            [6432, 7644],
            [6496, 7678],
            [6534, 7748]
          ]
        ]
      }
    },
    {
      "type": "Feature",
      "id": "HU.BU",
      "properties": {
        "hc-group": "admin1",
        "hc-middle-x": 0.41,
        "hc-middle-y": 0.5,
        "hc-key": "hu-bu",
        "hc-a2": "BU",
        "labelrank": "9",
        "hasc": "HU.BU",
        "alt-name": "Budapeste",
        "woe-id": "12577915",
        "subregion": "Pest",
        "fips": "HU05",
        "postal-code": "BU",
        "name": "Budapest",
        "country": "Hungary",
        "type-en": "Capital City",
        "region": "Central Hungary",
        "longitude": "19.1282",
        "woe-name": "Budapest",
        "latitude": "47.4757",
        "woe-label": "Budapest, HU, Hungary",
        "type": "Fovaros"
      },
      "geometry": {
        "type": "Polygon",
        "coordinates": [
          [
            [3624, 7079],
            [3637, 7162],
            [3668, 7260],
            [3617, 7422],
            [3606, 7560],
            [3703, 7572],
            [3784, 7628],
            [3860, 7631],
            [3928, 7586],
            [3963, 7539],
            [4061, 7474],
            [4232, 7339],
            [4194, 7249],
            [4118, 7193],
            [4086, 7155],
            [3932, 7050],
            [3885, 7057],
            [3806, 7109],
            [3624, 7079]
          ]
        ]
      }
    },
    {
      "type": "Feature",
      "id": "HU.ED",
      "properties": {
        "hc-group": "admin1",
        "hc-middle-x": 0.5,
        "hc-middle-y": 0.5,
        "hc-key": "hu-ed",
        "hc-a2": "ED",
        "labelrank": "7",
        "hasc": "HU.ED",
        "alt-name": null,
        "woe-id": "56043627",
        "subregion": "Pest",
        "fips": "HU43",
        "postal-code": "ED",
        "name": "Érd",
        "country": "Hungary",
        "type-en": "Urban county",
        "region": "Central Hungary",
        "longitude": "18.893",
        "woe-name": "Érd",
        "latitude": "47.3677",
        "woe-label": "Ã?rd, HU, Hungary",
        "type": "Megyei jogu város"
      },
      "geometry": {
        "type": "Polygon",
        "coordinates": [
          [
            [3637, 7162],
            [3624, 7079],
            [3588, 6961],
            [3546, 6928],
            [3492, 6937],
            [3417, 7054],
            [3486, 7125],
            [3460, 7204],
            [3453, 7283],
            [3494, 7300],
            [3589, 7219],
            [3637, 7162]
          ]
        ]
      }
    },
    {
      "type": "Feature",
      "id": "HU.SD",
      "properties": {
        "hc-group": "admin1",
        "hc-middle-x": 0.48,
        "hc-middle-y": 0.4,
        "hc-key": "hu-sd",
        "hc-a2": "SD",
        "labelrank": "7",
        "hasc": "HU.SD",
        "alt-name": null,
        "woe-id": "56043624",
        "subregion": "Csongrád",
        "fips": "HU34",
        "postal-code": "SD",
        "name": "Szeged",
        "country": "Hungary",
        "type-en": "Urban county",
        "region": "Great Southern Plain",
        "longitude": "20.1431",
        "woe-name": "Szeged",
        "latitude": "46.2689",
        "woe-label": "Szeged, HU, Hungary",
        "type": "Megyei jogu város"
      },
      "geometry": {
        "type": "Polygon",
        "coordinates": [
          [
            [5449, 4190],
            [5407, 4195],
            [5366, 4175],
            [5376, 4340],
            [5392, 4367],
            [5377, 4427],
            [5282, 4456],
            [5290, 4580],
            [5354, 4621],
            [5449, 4601],
            [5507, 4665],
            [5570, 4572],
            [5619, 4574],
            [5640, 4511],
            [5627, 4478],
            [5703, 4438],
            [5706, 4382],
            [5604, 4392],
            [5584, 4356],
            [5609, 4277],
            [5641, 4249],
            [5637, 4199],
            [5598, 4190],
            [5532, 4297],
            [5471, 4274],
            [5449, 4190]
          ]
        ]
      }
    },
    {
      "type": "Feature",
      "id": "HU.HV",
      "properties": {
        "hc-group": "admin1",
        "hc-middle-x": 0.51,
        "hc-middle-y": 0.51,
        "hc-key": "hu-hv",
        "hc-a2": "HV",
        "labelrank": "7",
        "hasc": "HU.HV",
        "alt-name": null,
        "woe-id": "56043623",
        "subregion": "Csongrád",
        "fips": "HU29",
        "postal-code": "HV",
        "name": "Hódmezôvásárhely",
        "country": "Hungary",
        "type-en": "Urban county",
        "region": "Great Southern Plain",
        "longitude": "20.3919",
        "woe-name": "Hódmezôvásárhely",
        "latitude": "46.3767",
        "woe-label": "Hódmezôvásárhely, HU, Hungary",
        "type": "Megyei jogu város"
      },
      "geometry": {
        "type": "Polygon",
        "coordinates": [
          [
            [5703, 4438],
            [5627, 4478],
            [5640, 4511],
            [5619, 4574],
            [5618, 4647],
            [5591, 4690],
            [5576, 4849],
            [5593, 4927],
            [5629, 4901],
            [5657, 4804],
            [5695, 4859],
            [5728, 4996],
            [5754, 5051],
            [5881, 5023],
            [6022, 5077],
            [6079, 5040],
            [6220, 4878],
            [6219, 4779],
            [6271, 4793],
            [6242, 4728],
            [6213, 4661],
            [6155, 4593],
            [6110, 4464],
            [6033, 4405],
            [5937, 4414],
            [5867, 4452],
            [5703, 4438]
          ]
        ]
      }
    },
    {
      "type": "Feature",
      "id": "HU.ST",
      "properties": {
        "hc-group": "admin1",
        "hc-middle-x": 0.51,
        "hc-middle-y": 0.32,
        "hc-key": "hu-st",
        "hc-a2": "ST",
        "labelrank": "7",
        "hasc": "HU.ST",
        "alt-name": null,
        "woe-id": "56043635",
        "subregion": "Nógrád",
        "fips": "HU41",
        "postal-code": "ST",
        "name": "Salgótarján",
        "country": "Hungary",
        "type-en": "Urban county",
        "region": "Northern Hungary",
        "longitude": "19.7907",
        "woe-name": "Salgótarján",
        "latitude": "48.1057",
        "woe-label": "Salgótarján, HU, Hungary",
        "type": "Megyei jogu város"
      },
      "geometry": {
        "type": "Polygon",
        "coordinates": [
          [
            [4956, 8904],
            [4986, 8879],
            [5043, 8900],
            [5081, 8887],
            [5172, 8819],
            [5108, 8753],
            [5032, 8701],
            [4987, 8625],
            [4864, 8650],
            [4903, 8840],
            [4956, 8904]
          ]
        ]
      }
    },
    {
      "type": "Feature",
      "id": "HU.MI",
      "properties": {
        "hc-group": "admin1",
        "hc-middle-x": 0.68,
        "hc-middle-y": 0.53,
        "hc-key": "hu-mi",
        "hc-a2": "MI",
        "labelrank": "7",
        "hasc": "HU.MI",
        "alt-name": null,
        "woe-id": "56043619",
        "subregion": "Borsod-Abaúj-Zemplén",
        "fips": "HU13",
        "postal-code": "MI",
        "name": "Miskolc",
        "country": "Hungary",
        "type-en": "Urban county",
        "region": "Northern Hungary",
        "longitude": "20.7319",
        "woe-name": "Miskolc",
        "latitude": "48.1181",
        "woe-label": "Miskolc, HU, Hungary",
        "type": "Megyei jogu város"
      },
      "geometry": {
        "type": "Polygon",
        "coordinates": [
          [
            [6093, 8647],
            [6091, 8756],
            [6064, 8784],
            [6116, 8845],
            [6199, 8851],
            [6275, 8916],
            [6439, 9039],
            [6506, 8991],
            [6562, 8991],
            [6621, 8955],
            [6665, 8890],
            [6697, 8801],
            [6696, 8730],
            [6732, 8665],
            [6740, 8611],
            [6688, 8552],
            [6545, 8523],
            [6378, 8636],
            [6327, 8707],
            [6231, 8702],
            [6152, 8685],
            [6093, 8647]
          ]
        ]
      }
    },
    {
      "type": "Feature",
      "id": "HU.NK",
      "properties": {
        "hc-group": "admin1",
        "hc-middle-x": 0.51,
        "hc-middle-y": 0.5,
        "hc-key": "hu-nk",
        "hc-a2": "NK",
        "labelrank": "7",
        "hasc": "HU.NK",
        "alt-name": null,
        "woe-id": "56043639",
        "subregion": "Zala",
        "fips": "HU32",
        "postal-code": "NK",
        "name": "Nagykanizsa",
        "country": "Hungary",
        "type-en": "Urban county",
        "region": "Western Transdanubia",
        "longitude": "16.9898",
        "woe-name": "Nagykanizsa",
        "latitude": "46.4513",
        "woe-label": "Nagykanizsa, HU, Hungary",
        "type": "Megyei jogu város"
      },
      "geometry": {
        "type": "Polygon",
        "coordinates": [
          [
            [517, 4976],
            [478, 4969],
            [489, 4898],
            [425, 4871],
            [341, 4887],
            [278, 4937],
            [284, 5207],
            [331, 5213],
            [346, 5306],
            [414, 5307],
            [425, 5205],
            [466, 5159],
            [475, 5073],
            [517, 4976]
          ]
        ]
      }
    },
    {
      "type": "Feature",
      "id": "HU.SO",
      "properties": {
        "hc-group": "admin1",
        "hc-middle-x": 0.59,
        "hc-middle-y": 0.35,
        "hc-key": "hu-so",
        "hc-a2": "SO",
        "labelrank": "7",
        "hasc": "HU.SO",
        "alt-name": null,
        "woe-id": "12577924",
        "subregion": "Somogy",
        "fips": "HU17",
        "postal-code": "SO",
        "name": "Somogy",
        "country": "Hungary",
        "type-en": "County",
        "region": "Southern Transdanubia",
        "longitude": "17.5491",
        "woe-name": "Somogy",
        "latitude": "46.3623",
        "woe-label": "Somogy, HU, Hungary",
        "type": "Megye"
      },
      "geometry": {
        "type": "Polygon",
        "coordinates": [
          [
            [489, 4898],
            [478, 4969],
            [517, 4976],
            [702, 5012],
            [726, 5087],
            [785, 5221],
            [790, 5530],
            [857, 5634],
            [925, 5685],
            [1032, 5673],
            [1099, 5704],
            [1183, 5711],
            [1517, 5836],
            [1814, 5997],
            [1887, 6014],
            [1953, 6079],
            [2035, 6111],
            [2193, 6192],
            [2279, 6182],
            [2359, 6142],
            [2421, 5988],
            [2409, 5959],
            [2403, 5825],
            [2411, 5759],
            [2302, 5714],
            [2259, 5644],
            [2242, 5572],
            [2208, 5502],
            [2184, 5324],
            [2132, 5232],
            [2097, 5124],
            [2109, 5027],
            [2143, 5006],
            [2181, 4782],
            [2149, 4756],
            [2103, 4671],
            [1917, 4655],
            [1759, 4464],
            [1707, 4427],
            [1628, 4427],
            [1551, 4403],
            [1502, 4351],
            [1500, 4207],
            [1469, 4134],
            [1370, 4089],
            [1411, 3943],
            [1384, 3897],
            [1400, 3825],
            [1502, 3674],
            [1494, 3606],
            [1411, 3593],
            [1400, 3687],
            [1315, 3795],
            [1187, 3842],
            [1048, 3855],
            [1013, 3826],
            [988, 3872],
            [915, 3858],
            [906, 3927],
            [887, 3898],
            [828, 3930],
            [873, 3959],
            [808, 3996],
            [771, 4158],
            [692, 4258],
            [560, 4269],
            [460, 4345],
            [423, 4410],
            [339, 4485],
            [289, 4584],
            [210, 4684],
            [196, 4731],
            [260, 4752],
            [298, 4702],
            [471, 4747],
            [503, 4784],
            [514, 4836],
            [489, 4898]
          ],
          [
            [1546, 4784],
            [1584, 4655],
            [1593, 4514],
            [1659, 4561],
            [1711, 4524],
            [1770, 4655],
            [1825, 4695],
            [1815, 4822],
            [1772, 4971],
            [1666, 4961],
            [1624, 4998],
            [1603, 4957],
            [1587, 4831],
            [1546, 4784]
          ]
        ]
      }
    },
    {
      "type": "Feature",
      "id": "HU.DU",
      "properties": {
        "hc-group": "admin1",
        "hc-middle-x": 0.51,
        "hc-middle-y": 0.48,
        "hc-key": "hu-du",
        "hc-a2": "DU",
        "labelrank": "7",
        "hasc": "HU.DU",
        "alt-name": null,
        "woe-id": "56043621",
        "subregion": "Fejér",
        "fips": "HU27",
        "postal-code": "DU",
        "name": "Dunaújváros",
        "country": "Hungary",
        "type-en": "Urban county",
        "region": "Central Transdanubia",
        "longitude": "18.8971",
        "woe-name": "Dunaújváros",
        "latitude": "46.9489",
        "woe-label": "Vas, HU, Hungary",
        "type": "Megyei jogu város"
      },
      "geometry": {
        "type": "Polygon",
        "coordinates": [
          [
            [3611, 6201],
            [3624, 6018],
            [3565, 5926],
            [3556, 5859],
            [3426, 5956],
            [3403, 6035],
            [3428, 6163],
            [3519, 6253],
            [3611, 6201]
          ]
        ]
      }
    },
    {
      "type": "Feature",
      "id": "HU.BK",
      "properties": {
        "hc-group": "admin1",
        "hc-middle-x": 0.48,
        "hc-middle-y": 0.47,
        "hc-key": "hu-bk",
        "hc-a2": "BK",
        "labelrank": "7",
        "hasc": "HU.BK",
        "alt-name": "Bacs-Bodrog-Kiskun",
        "woe-id": "12577911",
        "subregion": "Bács-Kiskun",
        "fips": "HU01",
        "postal-code": "BK",
        "name": "Bács-Kiskun",
        "country": "Hungary",
        "type-en": "County",
        "region": "Great Southern Plain",
        "longitude": "19.4699",
        "woe-name": "Bács-Kiskun",
        "latitude": "46.6096",
        "woe-label": "Bács-Kiskun, HU, Hungary",
        "type": "Megye"
      },
      "geometry": {
        "type": "Polygon",
        "coordinates": [
          [
            [3556, 5859],
            [3565, 5926],
            [3624, 6018],
            [3611, 6201],
            [3610, 6225],
            [3634, 6290],
            [3670, 6368],
            [3746, 6370],
            [3821, 6391],
            [3942, 6484],
            [4117, 6557],
            [4174, 6540],
            [4219, 6490],
            [4224, 6422],
            [4185, 6361],
            [4171, 6296],
            [4202, 6245],
            [4250, 6260],
            [4286, 6328],
            [4382, 6375],
            [4431, 6484],
            [4540, 6465],
            [4599, 6403],
            [4685, 6255],
            [4721, 6217],
            [4689, 6183],
            [4608, 6226],
            [4575, 6129],
            [4632, 5967],
            [4683, 5870],
            [4719, 5735],
            [4781, 5684],
            [4834, 5779],
            [4835, 5885],
            [4884, 5958],
            [4941, 5957],
            [4992, 5993],
            [4995, 6057],
            [5027, 6059],
            [5101, 6137],
            [5152, 6149],
            [5250, 6094],
            [5317, 6175],
            [5411, 6227],
            [5463, 6194],
            [5522, 6129],
            [5466, 6088],
            [5466, 6051],
            [5533, 6030],
            [5504, 5972],
            [5424, 6005],
            [5456, 5946],
            [5432, 5903],
            [5328, 5886],
            [5279, 5770],
            [5307, 5719],
            [5380, 5712],
            [5299, 5642],
            [5229, 5545],
            [5274, 5476],
            [5241, 5220],
            [5184, 5159],
            [5044, 5183],
            [4982, 5141],
            [4983, 5045],
            [5059, 4990],
            [5076, 4881],
            [5025, 4728],
            [4940, 4715],
            [4894, 4682],
            [4765, 4690],
            [4732, 4665],
            [4733, 4557],
            [4707, 4508],
            [4701, 4442],
            [4793, 4214],
            [4689, 4252],
            [4529, 4232],
            [4426, 4163],
            [4444, 4103],
            [4401, 4080],
            [4341, 4010],
            [4288, 3992],
            [4245, 3931],
            [4127, 3917],
            [4093, 3893],
            [4053, 3812],
            [4008, 3805],
            [3865, 3823],
            [3806, 3892],
            [3731, 3892],
            [3705, 3848],
            [3701, 3778],
            [3631, 3778],
            [3591, 3751],
            [3589, 3684],
            [3558, 3699],
            [3434, 3708],
            [3328, 3652],
            [3294, 3687],
            [3332, 3733],
            [3346, 3805],
            [3383, 3899],
            [3373, 3990],
            [3339, 4106],
            [3280, 4109],
            [3352, 4162],
            [3317, 4183],
            [3312, 4253],
            [3362, 4253],
            [3397, 4325],
            [3348, 4357],
            [3379, 4402],
            [3472, 4419],
            [3499, 4446],
            [3502, 4645],
            [3471, 4758],
            [3484, 4842],
            [3526, 4968],
            [3524, 5039],
            [3460, 5258],
            [3431, 5314],
            [3476, 5361],
            [3587, 5407],
            [3634, 5453],
            [3669, 5527],
            [3645, 5685],
            [3556, 5809],
            [3556, 5859]
          ]
        ]
      }
    },
    {
      "type": "Feature",
      "id": "HU.TB",
      "properties": {
        "hc-group": "admin1",
        "hc-middle-x": 0.43,
        "hc-middle-y": 0.41,
        "hc-key": "hu-tb",
        "hc-a2": "TB",
        "labelrank": "7",
        "hasc": "HU.TB",
        "alt-name": null,
        "woe-id": "56043626",
        "subregion": "Komárom-Esztergom",
        "fips": "HU38",
        "postal-code": "TB",
        "name": "Tatabánya",
        "country": "Hungary",
        "type-en": "Urban county",
        "region": "Central Transdanubia",
        "longitude": "18.4452",
        "woe-name": "Tatabánya",
        "latitude": "47.5667",
        "woe-label": "Tatabánya, HU, Hungary",
        "type": "Megyei jogu város"
      },
      "geometry": {
        "type": "Polygon",
        "coordinates": [
          [
            [2948, 7536],
            [2894, 7499],
            [2858, 7421],
            [2778, 7474],
            [2724, 7545],
            [2741, 7590],
            [2725, 7651],
            [2770, 7695],
            [2912, 7663],
            [2962, 7583],
            [2948, 7536]
          ]
        ]
      }
    },
    {
      "type": "Feature",
      "id": "HU.FE",
      "properties": {
        "hc-group": "admin1",
        "hc-middle-x": 0.56,
        "hc-middle-y": 0.63,
        "hc-key": "hu-fe",
        "hc-a2": "FE",
        "labelrank": "7",
        "hasc": "HU.FE",
        "alt-name": null,
        "woe-id": "12577917",
        "subregion": "Fejér",
        "fips": "HU08",
        "postal-code": "FE",
        "name": "Fejér",
        "country": "Hungary",
        "type-en": "County",
        "region": "Central Transdanubia",
        "longitude": "18.6516",
        "woe-name": "Fejér",
        "latitude": "46.989",
        "woe-label": "Fejér, HU, Hungary",
        "type": "Megye"
      },
      "geometry": {
        "type": "Polygon",
        "coordinates": [
          [
            [2858, 7421],
            [2894, 7499],
            [2948, 7536],
            [3217, 7543],
            [3276, 7414],
            [3354, 7310],
            [3371, 7250],
            [3358, 7183],
            [3417, 7054],
            [3492, 6937],
            [3546, 6928],
            [3571, 6888],
            [3550, 6772],
            [3515, 6704],
            [3499, 6566],
            [3533, 6406],
            [3634, 6290],
            [3610, 6225],
            [3611, 6201],
            [3519, 6253],
            [3428, 6163],
            [3403, 6035],
            [3426, 5956],
            [3556, 5859],
            [3482, 5837],
            [3410, 5791],
            [3247, 5596],
            [3117, 5528],
            [3069, 5542],
            [2961, 5726],
            [2895, 5700],
            [2854, 5640],
            [2766, 5652],
            [2700, 5686],
            [2592, 5781],
            [2496, 5779],
            [2411, 5759],
            [2403, 5825],
            [2409, 5959],
            [2421, 5988],
            [2359, 6142],
            [2424, 6235],
            [2451, 6348],
            [2436, 6409],
            [2455, 6563],
            [2434, 6621],
            [2391, 6649],
            [2337, 6783],
            [2272, 6852],
            [2255, 6916],
            [2267, 6979],
            [2325, 6993],
            [2276, 7098],
            [2306, 7163],
            [2305, 7232],
            [2322, 7287],
            [2399, 7297],
            [2427, 7339],
            [2460, 7337],
            [2598, 7198],
            [2683, 7218],
            [2649, 7269],
            [2674, 7302],
            [2755, 7340],
            [2858, 7421]
          ],
          [
            [2942, 6880],
            [2898, 6881],
            [2869, 6946],
            [2838, 6957],
            [2795, 6894],
            [2623, 6722],
            [2695, 6634],
            [2740, 6550],
            [2772, 6392],
            [2872, 6449],
            [2924, 6419],
            [3014, 6573],
            [3016, 6638],
            [2980, 6689],
            [3000, 6832],
            [2942, 6880]
          ]
        ]
      }
    },
    {
      "type": "Feature",
      "id": "HU.KE",
      "properties": {
        "hc-group": "admin1",
        "hc-middle-x": 0.35,
        "hc-middle-y": 0.41,
        "hc-key": "hu-ke",
        "hc-a2": "KE",
        "labelrank": "7",
        "hasc": "HU.KE",
        "alt-name": "Komarom",
        "woe-id": "12577921",
        "subregion": "Komárom-Esztergom",
        "fips": "HU12",
        "postal-code": "KE",
        "name": "Komárom-Esztergom",
        "country": "Hungary",
        "type-en": "County",
        "region": "Central Transdanubia",
        "longitude": "18.2244",
        "woe-name": "Komárom-Esztergom",
        "latitude": "47.6697",
        "woe-label": "Komárom-Esztergom, HU, Hungary",
        "type": "Megye"
      },
      "geometry": {
        "type": "Polygon",
        "coordinates": [
          [
            [3217, 7543],
            [2948, 7536],
            [2962, 7583],
            [2912, 7663],
            [2770, 7695],
            [2725, 7651],
            [2741, 7590],
            [2724, 7545],
            [2778, 7474],
            [2858, 7421],
            [2755, 7340],
            [2674, 7302],
            [2649, 7269],
            [2683, 7218],
            [2598, 7198],
            [2460, 7337],
            [2427, 7339],
            [2399, 7297],
            [2322, 7287],
            [2305, 7232],
            [2306, 7163],
            [2276, 7098],
            [2092, 7066],
            [2056, 7075],
            [2033, 7168],
            [1922, 7205],
            [1933, 7336],
            [1962, 7450],
            [1947, 7517],
            [1996, 7516],
            [2016, 7557],
            [1980, 7611],
            [2019, 7704],
            [1973, 7747],
            [1969, 7860],
            [1977, 7953],
            [1963, 8034],
            [2326, 8044],
            [2520, 8016],
            [2579, 8020],
            [2699, 8064],
            [3024, 8091],
            [3095, 8084],
            [3151, 8056],
            [3244, 8049],
            [3284, 8072],
            [3366, 8150],
            [3441, 8171],
            [3493, 8134],
            [3548, 8121],
            [3596, 8023],
            [3594, 7907],
            [3559, 7920],
            [3494, 7899],
            [3507, 7779],
            [3425, 7791],
            [3341, 7781],
            [3365, 7717],
            [3285, 7642],
            [3258, 7581],
            [3217, 7543]
          ]
        ]
      }
    },
    {
      "type": "Feature",
      "id": "HU.PE",
      "properties": {
        "hc-group": "admin1",
        "hc-middle-x": 0.58,
        "hc-middle-y": 0.6,
        "hc-key": "hu-pe",
        "hc-a2": "PE",
        "labelrank": "7",
        "hasc": "HU.PE",
        "alt-name": null,
        "woe-id": "12577923",
        "subregion": "Pest",
        "fips": "HU16",
        "postal-code": "PE",
        "name": "Pest",
        "country": "Hungary",
        "type-en": "County",
        "region": "Central Hungary",
        "longitude": "19.4435",
        "woe-name": "Pest",
        "latitude": "47.4344",
        "woe-label": "Pest, HU, Hungary",
        "type": "Megye"
      },
      "geometry": {
        "type": "Polygon",
        "coordinates": [
          [
            [3546, 6928],
            [3588, 6961],
            [3624, 7079],
            [3806, 7109],
            [3885, 7057],
            [3932, 7050],
            [4086, 7155],
            [4118, 7193],
            [4194, 7249],
            [4232, 7339],
            [4061, 7474],
            [3963, 7539],
            [3928, 7586],
            [3860, 7631],
            [3784, 7628],
            [3703, 7572],
            [3606, 7560],
            [3617, 7422],
            [3668, 7260],
            [3637, 7162],
            [3589, 7219],
            [3494, 7300],
            [3453, 7283],
            [3460, 7204],
            [3486, 7125],
            [3417, 7054],
            [3358, 7183],
            [3371, 7250],
            [3354, 7310],
            [3276, 7414],
            [3217, 7543],
            [3258, 7581],
            [3285, 7642],
            [3365, 7717],
            [3341, 7781],
            [3425, 7791],
            [3507, 7779],
            [3494, 7899],
            [3559, 7920],
            [3594, 7907],
            [3596, 8023],
            [3548, 8121],
            [3493, 8134],
            [3441, 8171],
            [3339, 8264],
            [3330, 8308],
            [3354, 8454],
            [3337, 8500],
            [3419, 8549],
            [3464, 8636],
            [3492, 8657],
            [3642, 8687],
            [3693, 8610],
            [3695, 8501],
            [3639, 8453],
            [3674, 8369],
            [3866, 8225],
            [3994, 8225],
            [4329, 8154],
            [4390, 8124],
            [4440, 8005],
            [4452, 7850],
            [4548, 7903],
            [4646, 7920],
            [4708, 7868],
            [4678, 7807],
            [4694, 7763],
            [4766, 7655],
            [4790, 7586],
            [4772, 7517],
            [4801, 7451],
            [4851, 7417],
            [4911, 7422],
            [4918, 7340],
            [5295, 6952],
            [5308, 6919],
            [5303, 6808],
            [5331, 6764],
            [5371, 6736],
            [5426, 6642],
            [5382, 6536],
            [5373, 6422],
            [5423, 6315],
            [5511, 6235],
            [5612, 6195],
            [5522, 6129],
            [5463, 6194],
            [5411, 6227],
            [5317, 6175],
            [5250, 6094],
            [5152, 6149],
            [5101, 6137],
            [5027, 6059],
            [4995, 6057],
            [4915, 6064],
            [4794, 6142],
            [4721, 6217],
            [4685, 6255],
            [4599, 6403],
            [4540, 6465],
            [4431, 6484],
            [4382, 6375],
            [4286, 6328],
            [4250, 6260],
            [4202, 6245],
            [4171, 6296],
            [4185, 6361],
            [4224, 6422],
            [4219, 6490],
            [4174, 6540],
            [4117, 6557],
            [3942, 6484],
            [3821, 6391],
            [3746, 6370],
            [3670, 6368],
            [3634, 6290],
            [3533, 6406],
            [3499, 6566],
            [3515, 6704],
            [3550, 6772],
            [3571, 6888],
            [3546, 6928]
          ]
        ]
      }
    },
    {
      "type": "Feature",
      "id": "HU.SK",
      "properties": {
        "hc-group": "admin1",
        "hc-middle-x": 0.51,
        "hc-middle-y": 0.6,
        "hc-key": "hu-sk",
        "hc-a2": "SK",
        "labelrank": "7",
        "hasc": "HU.SK",
        "alt-name": null,
        "woe-id": "56043638",
        "subregion": "Jász-Nagykun-Szolnok",
        "fips": "HU36",
        "postal-code": "SK",
        "name": "Szolnok",
        "country": "Hungary",
        "type-en": "Urban county",
        "region": "Northern Great Plain",
        "longitude": "20.168",
        "woe-name": "Szolnok",
        "latitude": "47.206",
        "woe-label": "Szolnok, HU, Hungary",
        "type": "Megyei jogu város"
      },
      "geometry": {
        "type": "Polygon",
        "coordinates": [
          [
            [5382, 6536],
            [5426, 6642],
            [5371, 6736],
            [5331, 6764],
            [5394, 6849],
            [5509, 6979],
            [5604, 6859],
            [5713, 6769],
            [5753, 6689],
            [5691, 6623],
            [5723, 6555],
            [5779, 6531],
            [5774, 6454],
            [5725, 6418],
            [5644, 6407],
            [5554, 6455],
            [5475, 6516],
            [5382, 6536]
          ]
        ]
      }
    },
    {
      "type": "Feature",
      "id": "HU.SZ",
      "properties": {
        "hc-group": "admin1",
        "hc-middle-x": 0.61,
        "hc-middle-y": 0.43,
        "hc-key": "hu-sz",
        "hc-a2": "SZ",
        "labelrank": "7",
        "hasc": "HU.SZ",
        "alt-name": "Szabolcs-Szatmár",
        "woe-id": "12577925",
        "subregion": "Szabolcs-Szatmár-Bereg",
        "fips": "HU18",
        "postal-code": "SZ",
        "name": "Szabolcs-Szatmár-Bereg",
        "country": "Hungary",
        "type-en": "County",
        "region": "Northern Great Plain",
        "longitude": "22.182",
        "woe-name": "Szabolcs-Szatmár-Bereg",
        "latitude": "47.9535",
        "woe-label": "Szabolcs-Szatmár-Bereg, HU, Hungary",
        "type": "Megye"
      },
      "geometry": {
        "type": "Polygon",
        "coordinates": [
          [
            [7071, 8423],
            [7081, 8485],
            [7109, 8532],
            [7177, 8578],
            [7242, 8584],
            [7290, 8628],
            [7339, 8578],
            [7479, 8580],
            [7532, 8596],
            [7572, 8636],
            [7588, 8710],
            [7562, 8781],
            [7593, 8888],
            [7639, 8933],
            [7853, 8942],
            [7915, 8913],
            [7975, 8913],
            [8094, 8989],
            [8138, 8996],
            [8218, 9068],
            [8317, 9075],
            [8370, 9106],
            [8465, 9237],
            [8538, 9231],
            [8581, 9258],
            [8669, 9436],
            [8701, 9473],
            [8769, 9511],
            [8879, 9479],
            [8857, 9370],
            [8911, 9371],
            [8922, 9269],
            [8940, 9222],
            [9019, 9105],
            [9084, 9109],
            [9140, 9092],
            [9213, 9107],
            [9333, 8956],
            [9406, 8779],
            [9552, 8784],
            [9634, 8820],
            [9771, 8720],
            [9821, 8618],
            [9804, 8534],
            [9778, 8501],
            [9851, 8427],
            [9788, 8321],
            [9700, 8272],
            [9659, 8222],
            [9672, 8169],
            [9650, 8136],
            [9565, 8101],
            [9482, 8007],
            [9364, 7971],
            [9309, 7979],
            [9191, 8039],
            [9143, 8026],
            [9119, 7933],
            [9057, 7904],
            [8984, 7914],
            [8889, 7865],
            [8800, 7748],
            [8791, 7684],
            [8752, 7628],
            [8724, 7549],
            [8689, 7593],
            [8655, 7728],
            [8627, 7769],
            [8554, 7686],
            [8512, 7726],
            [8521, 7788],
            [8474, 7869],
            [8363, 7929],
            [8309, 7926],
            [8253, 7810],
            [8224, 7780],
            [8162, 7834],
            [8029, 7871],
            [7998, 7900],
            [7920, 7916],
            [7894, 7951],
            [7745, 8067],
            [7751, 8199],
            [7769, 8324],
            [7753, 8373],
            [7703, 8390],
            [7643, 8354],
            [7387, 8333],
            [7317, 8305],
            [7186, 8408],
            [7071, 8423]
          ],
          [
            [7892, 8485],
            [7870, 8224],
            [8074, 8166],
            [8127, 8131],
            [8214, 8150],
            [8250, 8228],
            [8253, 8311],
            [8304, 8323],
            [8302, 8495],
            [8270, 8530],
            [8231, 8500],
            [8147, 8505],
            [8146, 8577],
            [8101, 8608],
            [8041, 8566],
            [8013, 8595],
            [7934, 8589],
            [7892, 8485]
          ]
        ]
      }
    },
    {
      "type": "Feature",
      "id": "HU.CS",
      "properties": {
        "hc-group": "admin1",
        "hc-middle-x": 0.41,
        "hc-middle-y": 0.35,
        "hc-key": "hu-cs",
        "hc-a2": "CS",
        "labelrank": "7",
        "hasc": "HU.CS",
        "alt-name": null,
        "woe-id": "12577916",
        "subregion": null,
        "fips": "HU06",
        "postal-code": "CS",
        "name": "Csongrád",
        "country": "Hungary",
        "type-en": "County",
        "region": "Great Southern Plain",
        "longitude": "20.1413",
        "woe-name": "Csongrád",
        "latitude": "46.5997",
        "woe-label": "Csongrád, HU, Hungary",
        "type": "Megye"
      },
      "geometry": {
        "type": "MultiPolygon",
        "coordinates": [
          [
            [
              [5366, 4175],
              [5319, 4170],
              [5251, 4209],
              [5147, 4220],
              [5082, 4207],
              [4920, 4143],
              [4892, 4149],
              [4793, 4214],
              [4701, 4442],
              [4707, 4508],
              [4733, 4557],
              [4732, 4665],
              [4765, 4690],
              [4894, 4682],
              [4940, 4715],
              [5025, 4728],
              [5076, 4881],
              [5059, 4990],
              [4983, 5045],
              [4982, 5141],
              [5044, 5183],
              [5184, 5159],
              [5241, 5220],
              [5274, 5476],
              [5229, 5545],
              [5299, 5642],
              [5380, 5712],
              [5498, 5634],
              [5684, 5694],
              [5741, 5639],
              [5800, 5622],
              [5853, 5663],
              [5963, 5712],
              [6174, 5642],
              [6226, 5594],
              [6229, 5445],
              [6207, 5333],
              [6212, 5159],
              [6237, 5111],
              [6284, 5090],
              [6262, 5014],
              [6227, 4955],
              [6220, 4878],
              [6079, 5040],
              [6022, 5077],
              [5881, 5023],
              [5754, 5051],
              [5728, 4996],
              [5695, 4859],
              [5657, 4804],
              [5629, 4901],
              [5593, 4927],
              [5576, 4849],
              [5591, 4690],
              [5618, 4647],
              [5619, 4574],
              [5570, 4572],
              [5507, 4665],
              [5449, 4601],
              [5354, 4621],
              [5290, 4580],
              [5282, 4456],
              [5377, 4427],
              [5392, 4367],
              [5376, 4340],
              [5366, 4175]
            ]
          ],
          [
            [
              [6546, 4443],
              [6468, 4383],
              [6477, 4295],
              [6463, 4264],
              [6412, 4250],
              [6401, 4193],
              [6344, 4149],
              [6252, 4130],
              [6220, 4138],
              [6157, 4193],
              [6026, 4236],
              [5986, 4173],
              [5724, 4168],
              [5657, 4084],
              [5569, 4161],
              [5499, 4154],
              [5449, 4190],
              [5471, 4274],
              [5532, 4297],
              [5598, 4190],
              [5637, 4199],
              [5641, 4249],
              [5609, 4277],
              [5584, 4356],
              [5604, 4392],
              [5706, 4382],
              [5703, 4438],
              [5867, 4452],
              [5937, 4414],
              [6033, 4405],
              [6110, 4464],
              [6155, 4593],
              [6213, 4661],
              [6242, 4728],
              [6323, 4727],
              [6409, 4749],
              [6455, 4725],
              [6501, 4645],
              [6484, 4533],
              [6546, 4443]
            ]
          ]
        ]
      }
    },
    {
      "type": "Feature",
      "id": "HU.BE",
      "properties": {
        "hc-group": "admin1",
        "hc-middle-x": 0.31,
        "hc-middle-y": 0.6,
        "hc-key": "hu-be",
        "hc-a2": "BE",
        "labelrank": "7",
        "hasc": "HU.BE",
        "alt-name": null,
        "woe-id": "12577913",
        "subregion": "Békés",
        "fips": "HU03",
        "postal-code": "BE",
        "name": "Békés",
        "country": "Hungary",
        "type-en": "County",
        "region": "Great Southern Plain",
        "longitude": "20.8362",
        "woe-name": "Békés",
        "latitude": "46.592",
        "woe-label": "Békés, HU, Hungary",
        "type": "Megye"
      },
      "geometry": {
        "type": "Polygon",
        "coordinates": [
          [
            [7909, 6220],
            [7963, 6157],
            [7934, 6041],
            [7847, 5963],
            [7844, 5847],
            [7814, 5802],
            [7756, 5786],
            [7702, 5716],
            [7651, 5570],
            [7707, 5524],
            [7673, 5433],
            [7596, 5407],
            [7532, 5295],
            [7497, 5277],
            [7403, 5272],
            [7379, 5242],
            [7363, 5108],
            [7293, 4992],
            [7289, 4944],
            [7337, 4854],
            [7347, 4802],
            [7310, 4774],
            [7209, 4759],
            [7166, 4676],
            [7159, 4572],
            [7111, 4478],
            [7053, 4473],
            [6976, 4379],
            [6947, 4368],
            [6904, 4409],
            [6830, 4407],
            [6740, 4440],
            [6676, 4428],
            [6631, 4461],
            [6546, 4443],
            [6484, 4533],
            [6501, 4645],
            [6455, 4725],
            [6409, 4749],
            [6323, 4727],
            [6242, 4728],
            [6271, 4793],
            [6219, 4779],
            [6220, 4878],
            [6227, 4955],
            [6262, 5014],
            [6284, 5090],
            [6237, 5111],
            [6212, 5159],
            [6207, 5333],
            [6229, 5445],
            [6226, 5594],
            [6174, 5642],
            [5963, 5712],
            [5939, 5790],
            [5957, 5858],
            [6020, 5913],
            [6131, 5904],
            [6177, 5968],
            [6224, 5955],
            [6261, 5987],
            [6306, 5942],
            [6419, 5992],
            [6436, 6062],
            [6412, 6205],
            [6473, 6278],
            [6466, 6323],
            [6606, 6491],
            [6670, 6493],
            [6730, 6545],
            [6760, 6605],
            [6799, 6620],
            [6852, 6708],
            [6883, 6724],
            [7081, 6595],
            [7149, 6571],
            [7221, 6563],
            [7326, 6512],
            [7359, 6444],
            [7355, 6208],
            [7375, 6171],
            [7444, 6131],
            [7430, 6073],
            [7460, 6044],
            [7513, 6033],
            [7625, 6065],
            [7693, 6064],
            [7801, 6176],
            [7909, 6220]
          ],
          [
            [6897, 5386],
            [7061, 5401],
            [7163, 5397],
            [7226, 5475],
            [7197, 5553],
            [7216, 5646],
            [7143, 5751],
            [6988, 5824],
            [6922, 5704],
            [6852, 5630],
            [6897, 5386]
          ]
        ]
      }
    },
    {
      "type": "Feature",
      "id": "HU.HB",
      "properties": {
        "hc-group": "admin1",
        "hc-middle-x": 0.37,
        "hc-middle-y": 0.58,
        "hc-key": "hu-hb",
        "hc-a2": "HB",
        "labelrank": "7",
        "hasc": "HU.HB",
        "alt-name": null,
        "woe-id": "12577919",
        "subregion": "Hajdú-Bihar",
        "fips": "HU07",
        "postal-code": "HB",
        "name": "Hajdú-Bihar",
        "country": "Hungary",
        "type-en": "County",
        "region": "Northern Great Plain",
        "longitude": "21.3746",
        "woe-name": "Hajdú-Bihar",
        "latitude": "47.2906",
        "woe-label": "Hajdú-Bihar, HU, Hungary",
        "type": "Megye"
      },
      "geometry": {
        "type": "Polygon",
        "coordinates": [
          [
            [7071, 8423],
            [7186, 8408],
            [7317, 8305],
            [7387, 8333],
            [7643, 8354],
            [7703, 8390],
            [7753, 8373],
            [7769, 8324],
            [7751, 8199],
            [7745, 8067],
            [7894, 7951],
            [7920, 7916],
            [7998, 7900],
            [8029, 7871],
            [8162, 7834],
            [8224, 7780],
            [8253, 7810],
            [8309, 7926],
            [8363, 7929],
            [8474, 7869],
            [8521, 7788],
            [8512, 7726],
            [8554, 7686],
            [8627, 7769],
            [8655, 7728],
            [8689, 7593],
            [8724, 7549],
            [8637, 7522],
            [8540, 7446],
            [8464, 7336],
            [8487, 7104],
            [8456, 7039],
            [8385, 7017],
            [8328, 6966],
            [8268, 6875],
            [8241, 6764],
            [8208, 6681],
            [8213, 6611],
            [8140, 6506],
            [8126, 6444],
            [8083, 6391],
            [8005, 6337],
            [7909, 6220],
            [7801, 6176],
            [7693, 6064],
            [7625, 6065],
            [7513, 6033],
            [7460, 6044],
            [7430, 6073],
            [7444, 6131],
            [7375, 6171],
            [7355, 6208],
            [7359, 6444],
            [7326, 6512],
            [7221, 6563],
            [7149, 6571],
            [7081, 6595],
            [6883, 6724],
            [6929, 6841],
            [6937, 6990],
            [6922, 7101],
            [6895, 7212],
            [6876, 7410],
            [6855, 7505],
            [6806, 7551],
            [6704, 7582],
            [6642, 7645],
            [6606, 7764],
            [6721, 7775],
            [6801, 7856],
            [6859, 7983],
            [6946, 7999],
            [6937, 8085],
            [6970, 8120],
            [6984, 8175],
            [6981, 8259],
            [7060, 8371],
            [7071, 8423]
          ],
          [
            [7753, 7891],
            [7653, 7795],
            [7588, 7602],
            [7553, 7466],
            [7557, 7347],
            [7666, 7348],
            [7699, 7235],
            [7790, 7184],
            [7811, 7090],
            [7907, 7090],
            [7995, 7204],
            [8055, 7216],
            [8121, 7152],
            [8228, 7277],
            [8259, 7367],
            [8262, 7515],
            [8208, 7610],
            [8147, 7686],
            [8091, 7668],
            [8040, 7602],
            [7968, 7560],
            [7923, 7619],
            [7857, 7832],
            [7777, 7820],
            [7758, 7748],
            [7734, 7766],
            [7753, 7891]
          ]
        ]
      }
    },
    {
      "type": "Feature",
      "id": "HU.SN",
      "properties": {
        "hc-group": "admin1",
        "hc-middle-x": 0.52,
        "hc-middle-y": 0.52,
        "hc-key": "hu-sn",
        "hc-a2": "SN",
        "labelrank": "7",
        "hasc": "HU.SN",
        "alt-name": null,
        "woe-id": "56043628",
        "subregion": "Gyor-Moson-Sopron",
        "fips": "HU22",
        "postal-code": "SN",
        "name": "Sopron",
        "country": "Hungary",
        "type-en": "Urban county",
        "region": "Western Transdanubia",
        "longitude": "16.6001",
        "woe-name": "Sopron",
        "latitude": "47.6911",
        "woe-label": "Sopron, HU, Hungary",
        "type": "Megyei jogu város"
      },
      "geometry": {
        "type": "Polygon",
        "coordinates": [
          [
            [-151, 7849],
            [-225, 7885],
            [-270, 7878],
            [-384, 7937],
            [-330, 8002],
            [-307, 7981],
            [-211, 8032],
            [-178, 8117],
            [-118, 8140],
            [-52, 8128],
            [91, 8056],
            [110, 7993],
            [61, 7934],
            [51, 7858],
            [-36, 7885],
            [-96, 7887],
            [-151, 7849]
          ]
        ]
      }
    },
    {
      "type": "Feature",
      "id": "HU.VA",
      "properties": {
        "hc-group": "admin1",
        "hc-middle-x": 0.67,
        "hc-middle-y": 0.39,
        "hc-key": "hu-va",
        "hc-a2": "VA",
        "labelrank": "7",
        "hasc": "HU.VA",
        "alt-name": null,
        "woe-id": "12577928",
        "subregion": "Vas",
        "fips": "HU22",
        "postal-code": "VA",
        "name": "Vas",
        "country": "Hungary",
        "type-en": "County",
        "region": "Western Transdanubia",
        "longitude": "16.814",
        "woe-name": "Vas",
        "latitude": "47.1693",
        "woe-label": "Vas, HU, Hungary",
        "type": "Megye"
      },
      "geometry": {
        "type": "Polygon",
        "coordinates": [
          [
            [-584, 5679],
            [-662, 5793],
            [-683, 5871],
            [-629, 5985],
            [-630, 6018],
            [-667, 6029],
            [-713, 6080],
            [-934, 6075],
            [-999, 6095],
            [-951, 6124],
            [-887, 6200],
            [-767, 6282],
            [-761, 6324],
            [-714, 6349],
            [-688, 6409],
            [-607, 6395],
            [-507, 6393],
            [-473, 6364],
            [-350, 6376],
            [-377, 6424],
            [-445, 6441],
            [-332, 6494],
            [-330, 6519],
            [-380, 6542],
            [-377, 6607],
            [-342, 6626],
            [-294, 6699],
            [-338, 6733],
            [-393, 6710],
            [-414, 6726],
            [-407, 6814],
            [-442, 6825],
            [-445, 6864],
            [-417, 6914],
            [-420, 6955],
            [-345, 6998],
            [-337, 7068],
            [-400, 7208],
            [-380, 7224],
            [-379, 7314],
            [-341, 7347],
            [-303, 7299],
            [-128, 7368],
            [-65, 7411],
            [-23, 7363],
            [59, 7340],
            [100, 7294],
            [146, 7300],
            [270, 7369],
            [307, 7334],
            [435, 7305],
            [611, 7395],
            [650, 7381],
            [615, 7274],
            [770, 7347],
            [810, 7314],
            [844, 7252],
            [911, 7160],
            [997, 7094],
            [888, 7051],
            [817, 6901],
            [826, 6834],
            [815, 6721],
            [836, 6474],
            [637, 6436],
            [590, 6376],
            [539, 6412],
            [501, 6414],
            [468, 6328],
            [400, 6292],
            [211, 6275],
            [190, 6232],
            [126, 6247],
            [67, 6210],
            [-94, 6208],
            [-156, 6183],
            [-239, 6045],
            [-316, 5981],
            [-352, 5922],
            [-423, 5881],
            [-499, 5885],
            [-490, 5803],
            [-584, 5679]
          ],
          [
            [-146, 6715],
            [-99, 6755],
            [-17, 6735],
            [-10, 6808],
            [19, 6922],
            [-9, 7036],
            [-75, 7048],
            [-180, 7016],
            [-239, 7035],
            [-248, 7008],
            [-191, 6757],
            [-146, 6715]
          ]
        ]
      }
    },
    {
      "type": "Feature",
      "id": "HU.SH",
      "properties": {
        "hc-group": "admin1",
        "hc-middle-x": 0.56,
        "hc-middle-y": 0.47,
        "hc-key": "hu-sh",
        "hc-a2": "SH",
        "labelrank": "7",
        "hasc": "HU.SH",
        "alt-name": null,
        "woe-id": "56043631",
        "subregion": "Vas",
        "fips": "HU37",
        "postal-code": "SH",
        "name": "Szombathely",
        "country": "Hungary",
        "type-en": "Urban county",
        "region": "Western Transdanubia",
        "longitude": "16.625",
        "woe-name": "Szombathely",
        "latitude": "47.2308",
        "woe-label": "Szombathely, HU, Hungary",
        "type": "Megyei jogu város"
      },
      "geometry": {
        "type": "Polygon",
        "coordinates": [
          [
            [-146, 6715],
            [-191, 6757],
            [-248, 7008],
            [-239, 7035],
            [-180, 7016],
            [-75, 7048],
            [-9, 7036],
            [19, 6922],
            [-10, 6808],
            [-17, 6735],
            [-99, 6755],
            [-146, 6715]
          ]
        ]
      }
    },
    {
      "type": "Feature",
      "id": "HU.BA",
      "properties": {
        "hc-group": "admin1",
        "hc-middle-x": 0.27,
        "hc-middle-y": 0.59,
        "hc-key": "hu-ba",
        "hc-a2": "BA",
        "labelrank": "7",
        "hasc": "HU.BA",
        "alt-name": null,
        "woe-id": "12577912",
        "subregion": null,
        "fips": "HU02",
        "postal-code": "BA",
        "name": "Baranya",
        "country": "Hungary",
        "type-en": "County",
        "region": "Southern Transdanubia",
        "longitude": "17.9611",
        "woe-name": "Baranya",
        "latitude": "45.9602",
        "woe-label": "Baranya, HU, Hungary",
        "type": "Megye"
      },
      "geometry": {
        "type": "Polygon",
        "coordinates": [
          [
            [3328, 3652],
            [3299, 3672],
            [3267, 3610],
            [3229, 3604],
            [3085, 3670],
            [3016, 3629],
            [2997, 3575],
            [2934, 3479],
            [2841, 3397],
            [2798, 3383],
            [2761, 3401],
            [2643, 3292],
            [2597, 3293],
            [2571, 3329],
            [2489, 3306],
            [2434, 3350],
            [2396, 3351],
            [2317, 3402],
            [2182, 3406],
            [2102, 3377],
            [1931, 3432],
            [1791, 3437],
            [1756, 3395],
            [1660, 3494],
            [1463, 3564],
            [1411, 3593],
            [1494, 3606],
            [1502, 3674],
            [1400, 3825],
            [1384, 3897],
            [1411, 3943],
            [1370, 4089],
            [1469, 4134],
            [1500, 4207],
            [1502, 4351],
            [1551, 4403],
            [1628, 4427],
            [1707, 4427],
            [1759, 4464],
            [1917, 4655],
            [2103, 4671],
            [2149, 4756],
            [2181, 4782],
            [2264, 4763],
            [2326, 4854],
            [2518, 4865],
            [2567, 4854],
            [2567, 4786],
            [2627, 4713],
            [2655, 4628],
            [2674, 4427],
            [2768, 4501],
            [2808, 4507],
            [2887, 4427],
            [2952, 4445],
            [3017, 4324],
            [3115, 4185],
            [3194, 4138],
            [3280, 4109],
            [3339, 4106],
            [3373, 3990],
            [3383, 3899],
            [3346, 3805],
            [3332, 3733],
            [3294, 3687],
            [3328, 3652]
          ],
          [
            [2221, 4199],
            [2201, 4106],
            [2229, 4056],
            [2202, 4000],
            [2316, 3898],
            [2374, 3868],
            [2419, 3894],
            [2502, 4046],
            [2585, 4029],
            [2600, 4057],
            [2579, 4149],
            [2525, 4298],
            [2456, 4258],
            [2325, 4284],
            [2221, 4199]
          ]
        ]
      }
    },
    {
      "type": "Feature",
      "id": "HU.GS",
      "properties": {
        "hc-group": "admin1",
        "hc-middle-x": 0.54,
        "hc-middle-y": 0.55,
        "hc-key": "hu-gs",
        "hc-a2": "GS",
        "labelrank": "7",
        "hasc": "HU.GS",
        "alt-name": "Gyor-Sopron",
        "woe-id": "12577918",
        "subregion": "Gyor-Moson-Sopron",
        "fips": "HU09",
        "postal-code": "GS",
        "name": "Gyor-Moson-Sopron",
        "country": "Hungary",
        "type-en": "County",
        "region": "Western Transdanubia",
        "longitude": "17.1682",
        "woe-name": "Gyor-Moson-Sopron",
        "latitude": "47.7217",
        "woe-label": "GyÅ?r-Moson-Sopron, HU, Hungary",
        "type": "Megye"
      },
      "geometry": {
        "type": "Polygon",
        "coordinates": [
          [
            [-65, 7411],
            [-42, 7427],
            [-43, 7522],
            [23, 7557],
            [42, 7586],
            [35, 7652],
            [-12, 7693],
            [-0, 7737],
            [-37, 7824],
            [-70, 7842],
            [-151, 7849],
            [-96, 7887],
            [-36, 7885],
            [51, 7858],
            [61, 7934],
            [110, 7993],
            [147, 7954],
            [235, 7935],
            [323, 8018],
            [343, 7956],
            [403, 7942],
            [530, 7966],
            [646, 7976],
            [679, 7989],
            [643, 8044],
            [635, 8209],
            [660, 8235],
            [638, 8294],
            [584, 8333],
            [585, 8358],
            [661, 8377],
            [704, 8419],
            [724, 8491],
            [705, 8504],
            [742, 8582],
            [727, 8602],
            [829, 8680],
            [889, 8712],
            [1025, 8670],
            [1127, 8650],
            [1175, 8606],
            [1326, 8382],
            [1411, 8339],
            [1479, 8236],
            [1529, 8245],
            [1584, 8207],
            [1639, 8134],
            [1740, 8074],
            [1871, 8032],
            [1963, 8034],
            [1977, 7953],
            [1969, 7860],
            [1973, 7747],
            [2019, 7704],
            [1980, 7611],
            [2016, 7557],
            [1996, 7516],
            [1947, 7517],
            [1962, 7450],
            [1933, 7336],
            [1831, 7431],
            [1828, 7386],
            [1770, 7406],
            [1742, 7382],
            [1686, 7411],
            [1612, 7389],
            [1543, 7340],
            [1480, 7371],
            [1433, 7345],
            [1352, 7360],
            [1317, 7313],
            [1222, 7285],
            [1167, 7298],
            [1115, 7339],
            [996, 7321],
            [967, 7328],
            [907, 7272],
            [844, 7252],
            [810, 7314],
            [770, 7347],
            [615, 7274],
            [650, 7381],
            [611, 7395],
            [435, 7305],
            [307, 7334],
            [270, 7369],
            [146, 7300],
            [100, 7294],
            [59, 7340],
            [-23, 7363],
            [-65, 7411]
          ],
          [
            [1712, 7992],
            [1638, 8012],
            [1482, 7965],
            [1446, 7851],
            [1351, 7784],
            [1399, 7701],
            [1423, 7706],
            [1477, 7666],
            [1542, 7709],
            [1644, 7705],
            [1814, 7794],
            [1829, 7836],
            [1814, 7915],
            [1784, 7996],
            [1712, 7992]
          ]
        ]
      }
    },
    {
      "type": "Feature",
      "id": "HU.TO",
      "properties": {
        "hc-group": "admin1",
        "hc-middle-x": 0.55,
        "hc-middle-y": 0.37,
        "hc-key": "hu-to",
        "hc-a2": "TO",
        "labelrank": "7",
        "hasc": "HU.TO",
        "alt-name": null,
        "woe-id": "12577927",
        "subregion": "Tolna",
        "fips": "HU21",
        "postal-code": "TO",
        "name": "Tolna",
        "country": "Hungary",
        "type-en": "County",
        "region": "Southern Transdanubia",
        "longitude": "18.5198",
        "woe-name": "Tolna",
        "latitude": "46.5078",
        "woe-label": "Tolna, HU, Hungary",
        "type": "Megye"
      },
      "geometry": {
        "type": "Polygon",
        "coordinates": [
          [
            [2181, 4782],
            [2143, 5006],
            [2109, 5027],
            [2097, 5124],
            [2132, 5232],
            [2184, 5324],
            [2208, 5502],
            [2242, 5572],
            [2259, 5644],
            [2302, 5714],
            [2411, 5759],
            [2496, 5779],
            [2592, 5781],
            [2700, 5686],
            [2766, 5652],
            [2854, 5640],
            [2895, 5700],
            [2961, 5726],
            [3069, 5542],
            [3117, 5528],
            [3247, 5596],
            [3410, 5791],
            [3482, 5837],
            [3556, 5859],
            [3556, 5809],
            [3645, 5685],
            [3669, 5527],
            [3634, 5453],
            [3587, 5407],
            [3476, 5361],
            [3431, 5314],
            [3460, 5258],
            [3524, 5039],
            [3526, 4968],
            [3484, 4842],
            [3471, 4758],
            [3502, 4645],
            [3499, 4446],
            [3472, 4419],
            [3379, 4402],
            [3348, 4357],
            [3397, 4325],
            [3362, 4253],
            [3312, 4253],
            [3317, 4183],
            [3352, 4162],
            [3280, 4109],
            [3194, 4138],
            [3115, 4185],
            [3017, 4324],
            [2952, 4445],
            [2887, 4427],
            [2808, 4507],
            [2768, 4501],
            [2674, 4427],
            [2655, 4628],
            [2627, 4713],
            [2567, 4786],
            [2567, 4854],
            [2518, 4865],
            [2326, 4854],
            [2264, 4763],
            [2181, 4782]
          ],
          [
            [3445, 4620],
            [3446, 4687],
            [3404, 4672],
            [3371, 4720],
            [3271, 4723],
            [3254, 4806],
            [3226, 4854],
            [3188, 4848],
            [3173, 4805],
            [3101, 4811],
            [3040, 4748],
            [3018, 4683],
            [3042, 4637],
            [3094, 4676],
            [3103, 4610],
            [3155, 4580],
            [3216, 4680],
            [3291, 4649],
            [3445, 4620]
          ]
        ]
      }
    },
    {
      "type": "Feature",
      "id": "HU.ZA",
      "properties": {
        "hc-group": "admin1",
        "hc-middle-x": 0.42,
        "hc-middle-y": 0.51,
        "hc-key": "hu-za",
        "hc-a2": "ZA",
        "labelrank": "7",
        "hasc": "HU.ZA",
        "alt-name": null,
        "woe-id": "12577930",
        "subregion": "Zala",
        "fips": "HU24",
        "postal-code": "ZA",
        "name": "Zala",
        "country": "Hungary",
        "type-en": "County",
        "region": "Western Transdanubia",
        "longitude": "16.7964",
        "woe-name": "Zala",
        "latitude": "46.6712",
        "woe-label": "Zala, HU, Hungary",
        "type": "Megye"
      },
      "geometry": {
        "type": "Polygon",
        "coordinates": [
          [
            [790, 5530],
            [785, 5221],
            [726, 5087],
            [702, 5012],
            [517, 4976],
            [475, 5073],
            [466, 5159],
            [425, 5205],
            [414, 5307],
            [346, 5306],
            [331, 5213],
            [284, 5207],
            [278, 4937],
            [341, 4887],
            [425, 4871],
            [489, 4898],
            [514, 4836],
            [503, 4784],
            [471, 4747],
            [298, 4702],
            [260, 4752],
            [196, 4731],
            [180, 4843],
            [137, 4898],
            [120, 4881],
            [83, 4917],
            [28, 4938],
            [3, 4905],
            [-14, 4948],
            [-62, 4981],
            [-142, 5107],
            [-244, 5157],
            [-263, 5129],
            [-370, 5208],
            [-387, 5310],
            [-439, 5360],
            [-494, 5457],
            [-577, 5520],
            [-588, 5553],
            [-517, 5608],
            [-523, 5653],
            [-584, 5679],
            [-490, 5803],
            [-499, 5885],
            [-423, 5881],
            [-352, 5922],
            [-316, 5981],
            [-239, 6045],
            [-156, 6183],
            [-94, 6208],
            [67, 6210],
            [126, 6247],
            [190, 6232],
            [211, 6275],
            [400, 6292],
            [468, 6328],
            [501, 6414],
            [539, 6412],
            [590, 6376],
            [637, 6436],
            [721, 6345],
            [689, 6267],
            [684, 5737],
            [656, 5575],
            [702, 5498],
            [790, 5530]
          ],
          [
            [94, 6119],
            [93, 5972],
            [148, 5930],
            [143, 5837],
            [248, 5851],
            [310, 5873],
            [292, 6055],
            [216, 6133],
            [94, 6119]
          ]
        ]
      }
    },
    {
      "type": "Feature",
      "id": "HU.ZE",
      "properties": {
        "hc-group": "admin1",
        "hc-middle-x": 0.47,
        "hc-middle-y": 0.49,
        "hc-key": "hu-ze",
        "hc-a2": "ZE",
        "labelrank": "7",
        "hasc": "HU.ZE",
        "alt-name": null,
        "woe-id": "56043640",
        "subregion": "Zala",
        "fips": "HU40",
        "postal-code": "ZE",
        "name": "Zalaegerszeg",
        "country": "Hungary",
        "type-en": "Urban county",
        "region": "Western Transdanubia",
        "longitude": "16.8447",
        "woe-name": "Zalaegerszeg",
        "latitude": "46.8452",
        "woe-label": "Zalaegerszeg, HU, Hungary",
        "type": "Megyei jogu város"
      },
      "geometry": {
        "type": "Polygon",
        "coordinates": [
          [
            [94, 6119],
            [216, 6133],
            [292, 6055],
            [310, 5873],
            [248, 5851],
            [143, 5837],
            [148, 5930],
            [93, 5972],
            [94, 6119]
          ]
        ]
      }
    },
    {
      "type": "Feature",
      "id": "HU.SS",
      "properties": {
        "hc-group": "admin1",
        "hc-middle-x": 0.35,
        "hc-middle-y": 0.51,
        "hc-key": "hu-ss",
        "hc-a2": "SS",
        "labelrank": "7",
        "hasc": "HU.SS",
        "alt-name": null,
        "woe-id": "56043632",
        "subregion": "Tolna",
        "fips": "HU42",
        "postal-code": "SS",
        "name": "Szekszárd",
        "country": "Hungary",
        "type-en": "Urban county",
        "region": "Southern Transdanubia",
        "longitude": "18.6981",
        "woe-name": "Szekszárd",
        "latitude": "46.356",
        "woe-label": "Szekszárd, HU, Hungary",
        "type": "Megyei jogu város"
      },
      "geometry": {
        "type": "Polygon",
        "coordinates": [
          [
            [3445, 4620],
            [3291, 4649],
            [3216, 4680],
            [3155, 4580],
            [3103, 4610],
            [3094, 4676],
            [3042, 4637],
            [3018, 4683],
            [3040, 4748],
            [3101, 4811],
            [3173, 4805],
            [3188, 4848],
            [3226, 4854],
            [3254, 4806],
            [3271, 4723],
            [3371, 4720],
            [3404, 4672],
            [3446, 4687],
            [3445, 4620]
          ]
        ]
      }
    },
    {
      "type": "Feature",
      "id": "HU.MC",
      "properties": {
        "hc-group": "admin1",
        "hc-middle-x": 0.5,
        "hc-middle-y": 0.63,
        "hc-key": "hu-mc",
        "hc-a2": "MC",
        "labelrank": "7",
        "hasc": "HU.MC",
        "alt-name": null,
        "woe-id": "56043637",
        "subregion": "Békés",
        "fips": "HU26",
        "postal-code": "MC",
        "name": "Békéscsaba",
        "country": "Hungary",
        "type-en": "Urban county",
        "region": "Great Southern Plain",
        "longitude": "21.0968",
        "woe-name": "Békéscsaba",
        "latitude": "46.7499",
        "woe-label": "Békéscsaba, HU, Hungary",
        "type": "Megyei jogu város"
      },
      "geometry": {
        "type": "Polygon",
        "coordinates": [
          [
            [6897, 5386],
            [6852, 5630],
            [6922, 5704],
            [6988, 5824],
            [7143, 5751],
            [7216, 5646],
            [7197, 5553],
            [7226, 5475],
            [7163, 5397],
            [7061, 5401],
            [6897, 5386]
          ]
        ]
      }
    },
    {
      "type": "Feature",
      "id": "HU.NY",
      "properties": {
        "hc-group": "admin1",
        "hc-middle-x": 0.5,
        "hc-middle-y": 0.48,
        "hc-key": "hu-ny",
        "hc-a2": "NY",
        "labelrank": "7",
        "hasc": "HU.NY",
        "alt-name": null,
        "woe-id": "56043636",
        "subregion": "Szabolcs-Szatmár-Bereg",
        "fips": "HU33",
        "postal-code": "NY",
        "name": "Nyíregyháza",
        "country": "Hungary",
        "type-en": "Urban county",
        "region": "Northern Great Plain",
        "longitude": "21.7602",
        "woe-name": "Nyíregyháza",
        "latitude": "47.9357",
        "woe-label": "Nyíregyháza, HU, Hungary",
        "type": "Megyei jogu város"
      },
      "geometry": {
        "type": "Polygon",
        "coordinates": [
          [
            [7892, 8485],
            [7934, 8589],
            [8013, 8595],
            [8041, 8566],
            [8101, 8608],
            [8146, 8577],
            [8147, 8505],
            [8231, 8500],
            [8270, 8530],
            [8302, 8495],
            [8304, 8323],
            [8253, 8311],
            [8250, 8228],
            [8214, 8150],
            [8127, 8131],
            [8074, 8166],
            [7870, 8224],
            [7892, 8485]
          ]
        ]
      }
    },
    {
      "type": "Feature",
      "id": "HU.DE",
      "properties": {
        "hc-group": "admin1",
        "hc-middle-x": 0.44,
        "hc-middle-y": 0.56,
        "hc-key": "hu-de",
        "hc-a2": "DE",
        "labelrank": "7",
        "hasc": "HU.DE",
        "alt-name": null,
        "woe-id": "56043620",
        "subregion": "Hajdú-Bihar",
        "fips": "HU07",
        "postal-code": "DE",
        "name": "Debrecen",
        "country": "Hungary",
        "type-en": "Urban county",
        "region": "Northern Great Plain",
        "longitude": "21.6192",
        "woe-name": "Debrecen",
        "latitude": "47.5252",
        "woe-label": "Debrecen, HU, Hungary",
        "type": "Megyei jogu város"
      },
      "geometry": {
        "type": "Polygon",
        "coordinates": [
          [
            [7753, 7891],
            [7734, 7766],
            [7758, 7748],
            [7777, 7820],
            [7857, 7832],
            [7923, 7619],
            [7968, 7560],
            [8040, 7602],
            [8091, 7668],
            [8147, 7686],
            [8208, 7610],
            [8262, 7515],
            [8259, 7367],
            [8228, 7277],
            [8121, 7152],
            [8055, 7216],
            [7995, 7204],
            [7907, 7090],
            [7811, 7090],
            [7790, 7184],
            [7699, 7235],
            [7666, 7348],
            [7557, 7347],
            [7553, 7466],
            [7588, 7602],
            [7653, 7795],
            [7753, 7891]
          ]
        ]
      }
    },
    {
      "type": "Feature",
      "id": "HU.EG",
      "properties": {
        "hc-group": "admin1",
        "hc-middle-x": 0.5,
        "hc-middle-y": 0.5,
        "hc-key": "hu-eg",
        "hc-a2": "EG",
        "labelrank": "7",
        "hasc": "HU.EG",
        "alt-name": null,
        "woe-id": "56043641",
        "subregion": "Heves",
        "fips": "HU28",
        "postal-code": "EG",
        "name": "Eger",
        "country": "Hungary",
        "type-en": "Urban county",
        "region": "Northern Hungary",
        "longitude": "20.3836",
        "woe-name": "Eger",
        "latitude": "47.9316",
        "woe-label": "Eger, HU, Hungary",
        "type": "Megyei jogu város"
      },
      "geometry": {
        "type": "Polygon",
        "coordinates": [
          [
            [5982, 8447],
            [5992, 8398],
            [6042, 8328],
            [6048, 8282],
            [6022, 8239],
            [5967, 8225],
            [5932, 8188],
            [5931, 8122],
            [5896, 8077],
            [5826, 8078],
            [5791, 8167],
            [5792, 8264],
            [5813, 8360],
            [5785, 8524],
            [5825, 8545],
            [5850, 8627],
            [5925, 8611],
            [5939, 8500],
            [5982, 8447]
          ]
        ]
      }
    },
    {
      "type": "Feature",
      "id": "HU.GY",
      "properties": {
        "hc-group": "admin1",
        "hc-middle-x": 0.61,
        "hc-middle-y": 0.44,
        "hc-key": "hu-gy",
        "hc-a2": "GY",
        "labelrank": "7",
        "hasc": "HU.GY",
        "alt-name": null,
        "woe-id": "56043629",
        "subregion": "Gyor-Moson-Sopron",
        "fips": "HU25",
        "postal-code": "GY",
        "name": "Gyôr",
        "country": "Hungary",
        "type-en": "Urban county",
        "region": "Western Transdanubia",
        "longitude": "17.6657",
        "woe-name": "Gyôr",
        "latitude": "47.6621",
        "woe-label": "Gyôr, HU, Hungary",
        "type": "Megyei jogu város"
      },
      "geometry": {
        "type": "Polygon",
        "coordinates": [
          [
            [1712, 7992],
            [1784, 7996],
            [1814, 7915],
            [1829, 7836],
            [1814, 7794],
            [1644, 7705],
            [1542, 7709],
            [1477, 7666],
            [1423, 7706],
            [1399, 7701],
            [1351, 7784],
            [1446, 7851],
            [1482, 7965],
            [1638, 8012],
            [1712, 7992]
          ]
        ]
      }
    },
    {
      "type": "Feature",
      "id": "HU.PS",
      "properties": {
        "hc-group": "admin1",
        "hc-middle-x": 0.49,
        "hc-middle-y": 0.44,
        "hc-key": "hu-ps",
        "hc-a2": "PS",
        "labelrank": "7",
        "hasc": "HU.PS",
        "alt-name": null,
        "woe-id": "56043625",
        "subregion": "Baranya",
        "fips": "HU15",
        "postal-code": "PS",
        "name": "Pécs",
        "country": "Hungary",
        "type-en": "Urban county",
        "region": "Southern Transdanubia",
        "longitude": "18.2337",
        "woe-name": "Pécs",
        "latitude": "46.0699",
        "woe-label": "Pécs, HU, Hungary",
        "type": "Megyei jogu város"
      },
      "geometry": {
        "type": "Polygon",
        "coordinates": [
          [
            [2221, 4199],
            [2325, 4284],
            [2456, 4258],
            [2525, 4298],
            [2579, 4149],
            [2600, 4057],
            [2585, 4029],
            [2502, 4046],
            [2419, 3894],
            [2374, 3868],
            [2316, 3898],
            [2202, 4000],
            [2229, 4056],
            [2201, 4106],
            [2221, 4199]
          ]
        ]
      }
    },
    {
      "type": "Feature",
      "id": "HU.SF",
      "properties": {
        "hc-group": "admin1",
        "hc-middle-x": 0.56,
        "hc-middle-y": 0.54,
        "hc-key": "hu-sf",
        "hc-a2": "SF",
        "labelrank": "7",
        "hasc": "HU.SF",
        "alt-name": null,
        "woe-id": "56043622",
        "subregion": "Fejér",
        "fips": "HU35",
        "postal-code": "SF",
        "name": "Székesfehérvár",
        "country": "Hungary",
        "type-en": "Urban county",
        "region": "Central Transdanubia",
        "longitude": "18.4618",
        "woe-name": "Székesfehérvár",
        "latitude": "47.1977",
        "woe-label": "Székesfehérvár, HU, Hungary",
        "type": "Megyei jogu város"
      },
      "geometry": {
        "type": "Polygon",
        "coordinates": [
          [
            [2942, 6880],
            [3000, 6832],
            [2980, 6689],
            [3016, 6638],
            [3014, 6573],
            [2924, 6419],
            [2872, 6449],
            [2772, 6392],
            [2740, 6550],
            [2695, 6634],
            [2623, 6722],
            [2795, 6894],
            [2838, 6957],
            [2869, 6946],
            [2898, 6881],
            [2942, 6880]
          ]
        ]
      }
    },
    {
      "type": "Feature",
      "id": "HU.VM",
      "properties": {
        "hc-group": "admin1",
        "hc-middle-x": 0.52,
        "hc-middle-y": 0.51,
        "hc-key": "hu-vm",
        "hc-a2": "VM",
        "labelrank": "7",
        "hasc": "HU.VM",
        "alt-name": null,
        "woe-id": "56043633",
        "subregion": "Veszprém",
        "fips": "HU39",
        "postal-code": "VM",
        "name": "Veszprém",
        "country": "Hungary",
        "type-en": "Urban county",
        "region": "Central Transdanubia",
        "longitude": "17.9145",
        "woe-name": "Veszprém",
        "latitude": "47.123",
        "woe-label": "Veszprém, HU, Hungary",
        "type": "Megyei jogu város"
      },
      "geometry": {
        "type": "Polygon",
        "coordinates": [
          [
            [1960, 6291],
            [1887, 6311],
            [1807, 6500],
            [1840, 6571],
            [1846, 6633],
            [1817, 6673],
            [1823, 6713],
            [1915, 6714],
            [1937, 6787],
            [1991, 6801],
            [2035, 6749],
            [2081, 6646],
            [2096, 6544],
            [2094, 6398],
            [2030, 6423],
            [1995, 6323],
            [1960, 6291]
          ]
        ]
      }
    },
    {
      "type": "Feature",
      "id": "HU.VE",
      "properties": {
        "hc-group": "admin1",
        "hc-middle-x": 0.4,
        "hc-middle-y": 0.44,
        "hc-key": "hu-ve",
        "hc-a2": "VE",
        "labelrank": "7",
        "hasc": "HU.VE",
        "alt-name": null,
        "woe-id": "12577929",
        "subregion": "Veszprém",
        "fips": "HU23",
        "postal-code": "VE",
        "name": "Veszprém",
        "country": "Hungary",
        "type-en": "County",
        "region": "Central Transdanubia",
        "longitude": "17.6638",
        "woe-name": "Veszprém",
        "latitude": "47.1365",
        "woe-label": "Veszprém, HU, Hungary",
        "type": "Megye"
      },
      "geometry": {
        "type": "Polygon",
        "coordinates": [
          [
            [2359, 6142],
            [2279, 6182],
            [2193, 6192],
            [2035, 6111],
            [1953, 6079],
            [1887, 6014],
            [1814, 5997],
            [1517, 5836],
            [1183, 5711],
            [1099, 5704],
            [1032, 5673],
            [925, 5685],
            [857, 5634],
            [790, 5530],
            [702, 5498],
            [656, 5575],
            [684, 5737],
            [689, 6267],
            [721, 6345],
            [637, 6436],
            [836, 6474],
            [815, 6721],
            [826, 6834],
            [817, 6901],
            [888, 7051],
            [997, 7094],
            [911, 7160],
            [844, 7252],
            [907, 7272],
            [967, 7328],
            [996, 7321],
            [1115, 7339],
            [1167, 7298],
            [1222, 7285],
            [1317, 7313],
            [1352, 7360],
            [1433, 7345],
            [1480, 7371],
            [1543, 7340],
            [1612, 7389],
            [1686, 7411],
            [1742, 7382],
            [1770, 7406],
            [1828, 7386],
            [1831, 7431],
            [1933, 7336],
            [1922, 7205],
            [2033, 7168],
            [2056, 7075],
            [2092, 7066],
            [2276, 7098],
            [2325, 6993],
            [2267, 6979],
            [2255, 6916],
            [2272, 6852],
            [2337, 6783],
            [2391, 6649],
            [2434, 6621],
            [2455, 6563],
            [2436, 6409],
            [2451, 6348],
            [2424, 6235],
            [2359, 6142]
          ],
          [
            [1960, 6291],
            [1995, 6323],
            [2030, 6423],
            [2094, 6398],
            [2096, 6544],
            [2081, 6646],
            [2035, 6749],
            [1991, 6801],
            [1937, 6787],
            [1915, 6714],
            [1823, 6713],
            [1817, 6673],
            [1846, 6633],
            [1840, 6571],
            [1807, 6500],
            [1887, 6311],
            [1960, 6291]
          ]
        ]
      }
    },
    {
      "type": "Feature",
      "id": "HU.KV",
      "properties": {
        "hc-group": "admin1",
        "hc-middle-x": 0.5,
        "hc-middle-y": 0.49,
        "hc-key": "hu-kv",
        "hc-a2": "KV",
        "labelrank": "7",
        "hasc": "HU.KV",
        "alt-name": null,
        "woe-id": "56043630",
        "subregion": "Somogy",
        "fips": "HU30",
        "postal-code": "KV",
        "name": "Kaposvár",
        "country": "Hungary",
        "type-en": "Urban county",
        "region": "Southern Transdanubia",
        "longitude": "17.7984",
        "woe-name": "Kaposvár",
        "latitude": "46.356",
        "woe-label": "Kaposvár, HU, Hungary",
        "type": "Megyei jogu város"
      },
      "geometry": {
        "type": "Polygon",
        "coordinates": [
          [
            [1546, 4784],
            [1587, 4831],
            [1603, 4957],
            [1624, 4998],
            [1666, 4961],
            [1772, 4971],
            [1815, 4822],
            [1825, 4695],
            [1770, 4655],
            [1711, 4524],
            [1659, 4561],
            [1593, 4514],
            [1584, 4655],
            [1546, 4784]
          ]
        ]
      }
    },
    {
      "type": "Feature",
      "id": "HU.KM",
      "properties": {
        "hc-group": "admin1",
        "hc-middle-x": 0.42,
        "hc-middle-y": 0.35,
        "hc-key": "hu-km",
        "hc-a2": "KM",
        "labelrank": "7",
        "hasc": "HU.KM",
        "alt-name": null,
        "woe-id": "56043634",
        "subregion": "Bács-Kiskun",
        "fips": "HU31",
        "postal-code": "KM",
        "name": "Kecskemét",
        "country": "Hungary",
        "type-en": "Urban county",
        "region": "Great Southern Plain",
        "longitude": "19.6684",
        "woe-name": "Kecskemét",
        "latitude": "46.9282",
        "woe-label": "Kecskemét, HU, Hungary",
        "type": "Megyei jogu város"
      },
      "geometry": {
        "type": "Polygon",
        "coordinates": [
          [
            [4995, 6057],
            [4992, 5993],
            [4941, 5957],
            [4884, 5958],
            [4835, 5885],
            [4834, 5779],
            [4781, 5684],
            [4719, 5735],
            [4683, 5870],
            [4632, 5967],
            [4575, 6129],
            [4608, 6226],
            [4689, 6183],
            [4721, 6217],
            [4794, 6142],
            [4915, 6064],
            [4995, 6057]
          ]
        ]
      }
    }
  ]
}
